[
  {
    "infinitivo": "tener",
    "tiempo": "imperfecto",
    "sujeto": "yo",
    "persona_base": "yo",
    "forma": "tenía",
    "traducción": "I used to have / I had",
    "tipo_verbo": [
      "irregular_imperfecto"
    ]
  },
  {
    "infinitivo": "hacer",
    "tiempo": "imperfecto",
    "sujeto": "tú",
    "persona_base": "tú",
    "forma": "hacías",
    "traducción": "you used to do / you were doing",
    "tipo_verbo": [
      "regular_imperfecto"
    ]
  },
  {
    "infinitivo": "estar",
    "tiempo": "imperfecto",
    "sujeto": "ella",
    "persona_base": "él/ella/Ud.",
    "forma": "estaba",
    "traducción": "she was",
    "tipo_verbo": [
      "regular_imperfecto"
    ]
  },
  {
    "infinitivo": "poder",
    "tiempo": "imperfecto",
    "sujeto": "nosotros",
    "persona_base": "nosotros",
    "forma": "podíamos",
    "traducción": "we were able to / we could",
    "tipo_verbo": [
      "regular_imperfecto"
    ]
  },
  {
    "infinitivo": "hablar",
    "tiempo": "imperfecto",
    "sujeto": "ellos",
    "persona_base": "ellos",
    "forma": "hablaban",
    "traducción": "they used to speak / they were speaking",
    "tipo_verbo": [
      "regular_imperfecto"
    ]
  },
  {
    "infinitivo": "querer",
    "tiempo": "imperfecto",
    "sujeto": "mis padres",
    "persona_base": "ellos/ellas/Uds.",
    "forma": "querían",
    "traducción": "my parents used to want / my parents wanted",
    "tipo_verbo": [
      "regular_imperfecto"
    ]
  },
  {
    "infinitivo": "ser",
    "tiempo": "imperfecto",
    "sujeto": "nosotros",
    "persona_base": "nosotros",
    "forma": "éramos",
    "traducción": "we used to be / we were being",
    "tipo_verbo": [
      "irregular_imperfecto"
    ]
  },
  {
    "infinitivo": "saber",
    "tiempo": "imperfecto",
    "sujeto": "yo",
    "persona_base": "yo",
    "forma": "sabía",
    "traducción": "I knew (state of knowledge)",
    "tipo_verbo": [
      "regular_imperfecto"
    ]
  },
  {
    "infinitivo": "poner",
    "tiempo": "imperfecto",
    "sujeto": "tú",
    "persona_base": "tú",
    "forma": "ponías",
    "traducción": "you used to put / you were putting",
    "tipo_verbo": [
      "regular_imperfecto"
    ]
  },
  {
    "infinitivo": "trabajar",
    "tiempo": "imperfecto",
    "sujeto": "nosotros",
    "persona_base": "nosotros",
    "forma": "trabajábamos",
    "traducción": "we used to work / we were working",
    "tipo_verbo": [
      "regular_imperfecto"
    ]
  },
  {
    "infinitivo": "venir",
    "tiempo": "imperfecto",
    "sujeto": "ella",
    "persona_base": "él/ella/Ud.",
    "forma": "venía",
    "traducción": "she used to come / she was coming",
    "tipo_verbo": [
      "regular_imperfecto"
    ]
  },
  {
    "infinitivo": "ver",
    "tiempo": "imperfecto",
    "sujeto": "nuestros amigos",
    "persona_base": "ellos/ellas/Uds.",
    "forma": "veían",
    "traducción": "our friends used to see/watch / our friends were watching",
    "tipo_verbo": [
      "irregular_imperfecto"
    ]
  },
  
  {
    "infinitivo": "leer",
    "tiempo": "imperfecto",
    "sujeto": "ellos/ellas/Uds.",
    "persona_base": "ellos/ellas/Uds.",
    "forma": "leían",
    "traducción": "they/you all used to read / were reading",
    "tipo_verbo": [
      "regular_imperfecto"
    ]
  },
  {
    "infinitivo": "caer",
    "tiempo": "imperfecto",
    "sujeto": "tú",
    "persona_base": "tú",
    "forma": "caías",
    "traducción": "you used to fall / you were falling",
    "tipo_verbo": [
      "regular_imperfecto"
    ]
  },
  {
    "infinitivo": "bailar",
    "tiempo": "imperfecto",
    "sujeto": "la clase",
    "persona_base": "él/ella/Ud.",
    "forma": "bailaba",
    "traducción": "la clase used to dance / the class was dancing",
    "tipo_verbo": [
      "regular_imperfecto"
    ]
  },
  {
    "infinitivo": "traer",
    "tiempo": "imperfecto",
    "sujeto": "nosotros",
    "persona_base": "nosotros",
    "forma": "traíamos",
    "traducción": "we used to bring / we were bringing",
    "tipo_verbo": [
      "regular_imperfecto"
    ]
  },
  {
    "infinitivo": "incluir",
    "tiempo": "imperfecto",
    "sujeto": "tú",
    "persona_base": "tú",
    "forma": "incluías",
    "traducción": "you used to include / you were including",
    "tipo_verbo": [
      "regular_imperfecto"
    ]
  },
  {
    "infinitivo": "construir",
    "tiempo": "imperfecto",
    "sujeto": "los arquitectos",
    "persona_base": "ellos/ellas/Uds.",
    "forma": "construían",
    "traducción": "the architects used to build / were building",
    "tipo_verbo": [
      "regular_imperfecto"
    ]
  },
  {
    "infinitivo": "imponer",
    "tiempo": "imperfecto",
    "sujeto": "él/ella/Ud.",
    "persona_base": "él/ella/Ud.",
    "forma": "imponía",
    "traducción": "he/she/you used to impose / was imposing",
    "tipo_verbo": [
      "regular_imperfecto"
    ]
  },
  {
    "infinitivo": "ir",
    "tiempo": "imperfecto",
    "sujeto": "yo",
    "persona_base": "yo",
    "forma": "iba",
    "traducción": "I was going to...",
    "tipo_verbo": [
      "irregular_imperfecto"
    ]
  }
]
