[
  {
    "spanish": "el programa de computación",
    "english": "software",
    "leccion": "2.2"
  },
  {
    "spanish": "publicar",
    "english": "to publish",
    "leccion": "8.2"
  },
  {
    "spanish": "la pasta de dientes",
    "english": "toothpaste",
    "leccion": "7.1",
    "seccion": "En el baño"
  },
  {
    "spanish": "jubilarse",
    "english": "to retire (from work)",
    "leccion": "9.1",
    "seccion": "Las etapas de la vida"
  },
  {
    "spanish": "el cuaderno",
    "english": "notebook",
    "leccion": "1.1",
    "seccion": "Los sustantivos"
  },
  {
    "spanish": "sacar/tomar fotos (f. pl.)",
    "english": "to take photos",
    "leccion": "5.1",
    "seccion": "Los viajes y las vacaciones"
  },
  {
    "spanish": "estudiar",
    "english": "to study",
    "leccion": "2.1",
    "seccion": "Verbos -ar y básicos"
  },
  {
    "spanish": "¿de quién...?",
    "english": "whose…? (sing.)",
    "leccion": "1.1",
    "seccion": "Preguntas básicas"
  },
  {
    "spanish": "musical",
    "english": "musical",
    "leccion": "8.2"
  },
  {
    "spanish": "el (teléfono) celular",
    "english": "cell phone",
    "leccion": "2.1"
  },
  {
    "spanish": "la chuleta (de cerdo)",
    "english": "(pork) chop",
    "leccion": "8.1",
    "seccion": "La carne y el pescado"
  },
  {
    "spanish": "el lápiz",
    "english": "pencil",
    "leccion": "1.1",
    "seccion": "Los sustantivos"
  },
  {
    "spanish": "el atún",
    "english": "tuna",
    "leccion": "8.1",
    "seccion": "La carne y el pescado"
  },
  {
    "spanish": "el estómago",
    "english": "stomach",
    "leccion": "1.1*"
  },
  {
    "spanish": "sentarse (e:ie)",
    "english": "to sit down",
    "leccion": "7.1",
    "seccion": "Los verbos reflexivos"
  },
  {
    "spanish": "la nariz",
    "english": "nose",
    "leccion": "1.1*"
  },
  {
    "spanish": "dormir (o:ue)",
    "english": "to sleep",
    "leccion": "4.1",
    "seccion": "Verbos"
  },
  {
    "spanish": "japonés, japonesa",
    "english": "Japanese",
    "leccion": "3.1",
    "seccion": "Nacionalidades"
  },
  {
    "spanish": "el día de fiesta",
    "english": "holiday",
    "leccion": "9.1",
    "seccion": "Las celebraciones"
  },
  {
    "spanish": "sábado",
    "english": "Saturday",
    "leccion": "2.1",
    "seccion": "Días de la semana y expresiones de clase"
  },
  {
    "spanish": "el inglés",
    "english": "English",
    "leccion": "2.1",
    "seccion": "Las materias"
  },
  {
    "spanish": "la infección",
    "english": "infection",
    "leccion": "1.2*"
  },
  {
    "spanish": "artístico/a",
    "english": "artistic",
    "leccion": "8.1"
  },
  {
    "spanish": "el impermeable",
    "english": "raincoat",
    "leccion": "6.1",
    "seccion": "La ropa"
  },
  {
    "spanish": "el reproductor de DVD",
    "english": "DVD player",
    "leccion": "2.2"
  },
  {
    "spanish": "el béisbol",
    "english": "baseball",
    "leccion": "4.1",
    "seccion": "Deportes"
  },
  {
    "spanish": "la estación de tren",
    "english": "train station",
    "leccion": "5.1",
    "seccion": "Los viajes y las vacaciones"
  },
  {
    "spanish": "guapo/a",
    "english": "good-looking",
    "leccion": "3.1",
    "seccion": "Adjetivos descriptivos"
  },
  {
    "spanish": "el/la sobrino/a",
    "english": "nephew/niece",
    "leccion": "3.1",
    "seccion": "Familia y parientes"
  },
  {
    "spanish": "el regalo",
    "english": "gift",
    "leccion": "6.1",
    "seccion": "Ir de compras"
  }
]