[
  {
    "spanish": "descansar",
    "english": "to rest",
    "leccion": "2.1",
    "seccion": "Verbos -ar y básicos"
  },
  {
    "spanish": "el agua (mineral)",
    "english": "(mineral) water",
    "leccion": "8.1",
    "seccion": "Las bebidas"
  },
  {
    "spanish": "¿Cómo se llama usted?",
    "english": "What’s your name? (formal)",
    "leccion": "1.1",
    "seccion": "Identificación personal"
  },
  {
    "spanish": "el boleto",
    "english": "ticket",
    "leccion": "8.1"
  },
  {
    "spanish": "barato/a",
    "english": "cheap",
    "leccion": "6.1",
    "seccion": "Adjetivos"
  },
  {
    "spanish": "alto/a",
    "english": "tall",
    "leccion": "3.1",
    "seccion": "Adjetivos descriptivos"
  },
  {
    "spanish": "la ópera",
    "english": "opera",
    "leccion": "8.2"
  },
  {
    "spanish": "el/la abuelo/a",
    "english": "grandfather/grandmother",
    "leccion": "3.1",
    "seccion": "Familia y parientes"
  },
  {
    "spanish": "nuevo/a",
    "english": "new",
    "leccion": "6.1",
    "seccion": "Adjetivos"
  },
  {
    "spanish": "la semana",
    "english": "week",
    "leccion": "2.1",
    "seccion": "Días de la semana y expresiones de clase"
  },
  {
    "spanish": "Te presento a...",
    "english": "I would like to introduce you to (name). (informal)",
    "leccion": "1.1",
    "seccion": "Identificación personal"
  },
  {
    "spanish": "el café",
    "english": "café",
    "leccion": "4.1",
    "seccion": "Lugares"
  },
  {
    "spanish": "conmigo",
    "english": "with me",
    "leccion": "9.1",
    "seccion": "Palabras adicionales"
  },
  {
    "spanish": "el flan (de caramelo)",
    "english": "baked (caramel) custard",
    "leccion": "9.1",
    "seccion": "Los postres y otras comidas"
  },
  {
    "spanish": "desear",
    "english": "to wish; to desire",
    "leccion": "2.1",
    "seccion": "Verbos -ar y básicos"
  },
  {
    "spanish": "la zanahoria",
    "english": "carrot",
    "leccion": "8.1",
    "seccion": "Las verduras"
  },
  {
    "spanish": "ver películas (f., pl.)",
    "english": "to watch movies",
    "leccion": "4.1",
    "seccion": "Actividades"
  },
  {
    "spanish": "casado/a",
    "english": "married",
    "leccion": "9.1",
    "seccion": "Las relaciones personales"
  },
  {
    "spanish": "peinarse",
    "english": "to comb one's hair",
    "leccion": "7.1",
    "seccion": "Los verbos reflexivos"
  },
  {
    "spanish": "el paisaje",
    "english": "landscape",
    "leccion": "5.1",
    "seccion": "Los viajes y las vacaciones"
  },
  {
    "spanish": "hacer (wind)surf",
    "english": "to (wind)surf",
    "leccion": "5.1",
    "seccion": "Los viajes y las vacaciones"
  },
  {
    "spanish": "el jabón",
    "english": "soap",
    "leccion": "7.1",
    "seccion": "En el baño"
  },
  {
    "spanish": "el/la profesor(a)",
    "english": "teacher",
    "leccion": "1.1",
    "seccion": "Los sustantivos"
  },
  {
    "spanish": "aprender (a + inf.)",
    "english": "to learn",
    "leccion": "3.1",
    "seccion": "Verbos regulares y tener/venir"
  },
  {
    "spanish": "la pasta de dientes",
    "english": "toothpaste",
    "leccion": "7.1",
    "seccion": "En el baño"
  },
  {
    "spanish": "el pasatiempo",
    "english": "pastime; hobby",
    "leccion": "4.1",
    "seccion": "Actividades"
  },
  {
    "spanish": "el/la escritor(a)",
    "english": "writer",
    "leccion": "8.2"
  },
  {
    "spanish": "triste",
    "english": "sad",
    "leccion": "5.1",
    "seccion": "Adjetivos"
  },
  {
    "spanish": "el pavo",
    "english": "turkey",
    "leccion": "8.1",
    "seccion": "La carne y el pescado"
  },
  {
    "spanish": "el/la cliente/a",
    "english": "customer",
    "leccion": "6.1",
    "seccion": "Ir de compras"
  }
]