[
  {
    "spanish": "aprender (a + inf.)",
    "english": "to learn",
    "leccion": "3.1",
    "seccion": "Verbos regulares y tener/venir"
  },
  {
    "spanish": "alegrarse (de)",
    "english": "to be happy",
    "leccion": "4.4"
  },
  {
    "spanish": "el/la dramaturgo/a",
    "english": "playwright",
    "leccion": "10.2"
  },
  {
    "spanish": "tratar de (+ inf.)",
    "english": "to try (to do something)",
    "leccion": "6.1"
  },
  {
    "spanish": "el impuesto de ventas",
    "english": "sales tax",
    "leccion": "8.3"
  },
  {
    "spanish": "por fin",
    "english": "finally",
    "leccion": "2.4"
  },
  {
    "spanish": "el cine",
    "english": "movie theater; cinema",
    "leccion": "2.2"
  },
  {
    "spanish": "el/la joven",
    "english": "youth; young person",
    "leccion": "1.1",
    "seccion": "Los sustantivos"
  },
  {
    "spanish": "fabricar",
    "english": "to manufacture; to make",
    "leccion": "7.3"
  },
  {
    "spanish": "la inversión extranjera",
    "english": "foreign investment",
    "leccion": "8.3"
  },
  {
    "spanish": "solicitar",
    "english": "to apply (for a job)",
    "leccion": "7.3"
  },
  {
    "spanish": "el avance",
    "english": "advance; breakthrough",
    "leccion": "7.2"
  },
  {
    "spanish": "con frecuencia",
    "english": "frequently",
    "leccion": "1.4*"
  },
  {
    "spanish": "la acuarela",
    "english": "watercolor",
    "leccion": "10.2"
  },
  {
    "spanish": "el canal",
    "english": "channel",
    "leccion": "8.3"
  },
  {
    "spanish": "el/la reportero/a",
    "english": "reporter",
    "leccion": "9.1"
  },
  {
    "spanish": "las relaciones personales",
    "english": "personal relationships",
    "leccion": "1.2"
  },
  {
    "spanish": "didáctico/a",
    "english": "educational",
    "leccion": "10.2"
  },
  {
    "spanish": "recomendable",
    "english": "recommendable; advisable",
    "leccion": "5.2"
  },
  {
    "spanish": "la erosión",
    "english": "erosion",
    "leccion": "6.3"
  },
  {
    "spanish": "el ecoturismo",
    "english": "ecotourism",
    "leccion": "5.3"
  },
  {
    "spanish": "la tensión alta",
    "english": "high blood pressure",
    "leccion": "4.1"
  },
  {
    "spanish": "el mar",
    "english": "sea",
    "leccion": "6.1"
  },
  {
    "spanish": "ensuciar",
    "english": "to get (something) dirty",
    "leccion": "3.3"
  },
  {
    "spanish": "el titular",
    "english": "headline",
    "leccion": "9.3"
  },
  {
    "spanish": "las actualidades",
    "english": "news; current events",
    "leccion": "9.2"
  },
  {
    "spanish": "la limpieza",
    "english": "cleaning",
    "leccion": "3.1"
  },
  {
    "spanish": "llegar",
    "english": "to arrive",
    "leccion": "2.1",
    "seccion": "Verbos -ar y básicos"
  },
  {
    "spanish": "la obra de teatro",
    "english": "play",
    "leccion": "10.1"
  },
  {
    "spanish": "(al) este",
    "english": "(to the) east",
    "leccion": "5.2"
  }
]