[
  {
    "spanish": "Saludos a...",
    "english": "Greetings to…",
    "leccion": "1.1",
    "seccion": "Despedidas"
  },
  {
    "spanish": "lejano/a",
    "english": "distant",
    "leccion": "5.3"
  },
  {
    "spanish": "el cariño",
    "english": "affection",
    "leccion": "1.2"
  },
  {
    "spanish": "encontrar(se) (o:ue)",
    "english": "to meet (each other); to run into (each other)",
    "leccion": "2.4"
  },
  {
    "spanish": "el reloj",
    "english": "clock; watch",
    "leccion": "2.1",
    "seccion": "Objetos del aula"
  },
  {
    "spanish": "la cerveza",
    "english": "beer",
    "leccion": "8.1",
    "seccion": "Las bebidas"
  },
  {
    "spanish": "la computadora (portátil)",
    "english": "(portable) computer; (laptop)",
    "leccion": "2.2"
  },
  {
    "spanish": "el deber",
    "english": "responsibility; obligation",
    "leccion": "9.2"
  },
  {
    "spanish": "echar (una carta) al buzón",
    "english": "to put (a letter) in the mailbox; to mail",
    "leccion": "5.2"
  },
  {
    "spanish": "con tal (de) que",
    "english": "provided (that)",
    "leccion": "4.5"
  },
  {
    "spanish": "español(a)",
    "english": "Spanish",
    "leccion": "3.1",
    "seccion": "Nacionalidades"
  },
  {
    "spanish": "hacer las maletas",
    "english": "to pack",
    "leccion": "5.1"
  },
  {
    "spanish": "la alimentación",
    "english": "diet (nutrition)",
    "leccion": "4.2"
  },
  {
    "spanish": "la manta",
    "english": "blanket",
    "leccion": "3.2"
  },
  {
    "spanish": "incluido/a",
    "english": "included",
    "leccion": "5.2"
  },
  {
    "spanish": "casado/a",
    "english": "married",
    "leccion": "9.1",
    "seccion": "Las relaciones personales"
  },
  {
    "spanish": "clásico/a",
    "english": "classical",
    "leccion": "8.1"
  },
  {
    "spanish": "nuevo/a",
    "english": "new",
    "leccion": "6.1",
    "seccion": "Adjetivos"
  },
  {
    "spanish": "la universidad",
    "english": "university; college",
    "leccion": "2.1",
    "seccion": "Lugares en el campus"
  },
  {
    "spanish": "el reembolso",
    "english": "refund",
    "leccion": "3.2"
  },
  {
    "spanish": "así",
    "english": "like this; so",
    "leccion": "1.4*"
  },
  {
    "spanish": "mientras",
    "english": "while",
    "leccion": "1.4*"
  },
  {
    "spanish": "desafiar",
    "english": "to challenge",
    "leccion": "2.3"
  },
  {
    "spanish": "listo/a",
    "english": "ready; smart",
    "leccion": "5.1",
    "seccion": "Adjetivos"
  },
  {
    "spanish": "entonces",
    "english": "then",
    "leccion": "7.1",
    "seccion": "Palabras de secuencia"
  },
  {
    "spanish": "el/la bombero/a",
    "english": "firefighter",
    "leccion": "7.1"
  },
  {
    "spanish": "encontrar (o:ue)",
    "english": "to find",
    "leccion": "4.1",
    "seccion": "Verbos"
  },
  {
    "spanish": "alojarse",
    "english": "to stay",
    "leccion": "5.2"
  },
  {
    "spanish": "la sala",
    "english": "living room",
    "leccion": "3.1"
  },
  {
    "spanish": "aliviar la tensión",
    "english": "to reduce tension",
    "leccion": "6.1"
  }
]