[
  {
    "spanish": "Cuba",
    "english": "Cuba",
    "leccion": "1.1",
    "seccion": "Países"
  },
  {
    "spanish": "reservar",
    "english": "to reserve",
    "leccion": "5.2"
  },
  {
    "spanish": "el mono",
    "english": "monkey",
    "leccion": "6.1"
  },
  {
    "spanish": "depositar",
    "english": "to deposit",
    "leccion": "8.2"
  },
  {
    "spanish": "Es malo que…",
    "english": "It’s bad that...",
    "leccion": "3.4"
  },
  {
    "spanish": "estar contaminado/a",
    "english": "to be polluted",
    "leccion": "4.3"
  },
  {
    "spanish": "guardar",
    "english": "to save",
    "leccion": "2.2"
  },
  {
    "spanish": "español(a)",
    "english": "Spanish",
    "leccion": "3.1",
    "seccion": "Nacionalidades"
  },
  {
    "spanish": "hacer",
    "english": "to do; to make",
    "leccion": "4.1",
    "seccion": "Verbos"
  },
  {
    "spanish": "el pasaje (de ida y vuelta)",
    "english": "(round-trip) ticket",
    "leccion": "5.1",
    "seccion": "Los viajes y las vacaciones"
  },
  {
    "spanish": "la bienvenida",
    "english": "welcome",
    "leccion": "5.1"
  },
  {
    "spanish": "el tratamiento",
    "english": "treatment",
    "leccion": "4.3"
  },
  {
    "spanish": "mentiroso/a",
    "english": "lying",
    "leccion": "1.1"
  },
  {
    "spanish": "el/la (bio)químico/a",
    "english": "(bio)chemist",
    "leccion": "7.2"
  },
  {
    "spanish": "el/la aspirante",
    "english": "candidate; applicant",
    "leccion": "7.3"
  },
  {
    "spanish": "el dolor (de cabeza)",
    "english": "(head)ache; pain",
    "leccion": "1.2*"
  },
  {
    "spanish": "... de horror",
    "english": "horror",
    "leccion": "8.3"
  },
  {
    "spanish": "de repente",
    "english": "suddenly",
    "leccion": "3.3"
  },
  {
    "spanish": "político/a",
    "english": "political",
    "leccion": "9.2"
  },
  {
    "spanish": "la prueba",
    "english": "test; quiz",
    "leccion": "2.1",
    "seccion": "Educación"
  },
  {
    "spanish": "tener buen aspecto",
    "english": "to look healthy",
    "leccion": "4.1"
  },
  {
    "spanish": "la contaminación",
    "english": "pollution; contamination",
    "leccion": "6.3"
  },
  {
    "spanish": "hacer cola",
    "english": "to stand in line",
    "leccion": "5.1"
  },
  {
    "spanish": "revolucionario/a",
    "english": "revolutionary",
    "leccion": "7.3"
  },
  {
    "spanish": "el/la cantante",
    "english": "singer",
    "leccion": "2.3"
  },
  {
    "spanish": "la nutrición",
    "english": "nutrition",
    "leccion": "6.2"
  },
  {
    "spanish": "ir de compras",
    "english": "to go shopping",
    "leccion": "3.2"
  },
  {
    "spanish": "la cuenta corriente",
    "english": "checking account",
    "leccion": "8.2"
  },
  {
    "spanish": "el puesto",
    "english": "position; job",
    "leccion": "8.1"
  },
  {
    "spanish": "pedir (e:i) prestado/a",
    "english": "to borrow",
    "leccion": "8.2"
  }
]