[
  {
    "infinitivo": "hablar",
    "tiempo": "futuro",
    "sujeto": "yo",
    "forma": "hablaré",
    "traducción": "speak",
    "contexto": "___ español en la clase.",
    "tags": [
      "ar"
    ]
  },
  {
    "infinitivo": "hablar",
    "tiempo": "futuro",
    "sujeto": "tú",
    "forma": "hablarás",
    "traducción": "speak",
    "contexto": "___ con tus amigos la próxima semana."
  },
  {
    "infinitivo": "hablar",
    "tiempo": "futuro",
    "sujeto": "él",
    "forma": "hablará",
    "traducción": "speak",
    "contexto": "___ con su profesor durante la reunión."
  },
  {
    "infinitivo": "hablar",
    "tiempo": "futuro",
    "sujeto": "ella",
    "forma": "hablará",
    "traducción": "speak",
    "contexto": "___ muy rápido durante la presentación."
  },
  {
    "infinitivo": "hablar",
    "tiempo": "futuro",
    "sujeto": "nosotros",
    "forma": "hablaremos",
    "traducción": "speak",
    "contexto": "___ mucho durante la cena de mañana."
  },
  {
    "infinitivo": "hablar",
    "tiempo": "futuro",
    "sujeto": "vosotros",
    "forma": "hablaréis",
    "traducción": "speak (en España)",
    "contexto": "¿___ en español durante el viaje? (España)"
  },
  {
    "infinitivo": "hablar",
    "tiempo": "futuro",
    "sujeto": "ellos",
    "forma": "hablarán",
    "traducción": "speak",
    "contexto": "Se ___ por teléfono esta noche."
  },
  {
    "infinitivo": "tener",
    "tiempo": "futuro",
    "sujeto": "yo",
    "forma": "tendré",
    "traducción": "have",
    "contexto": "___ mucho trabajo la próxima semana.",
    "tags": [
      "er",
      "stem-change",
      "yo-irregular"
    ]
  },
  {
    "infinitivo": "tener",
    "tiempo": "futuro",
    "sujeto": "tú",
    "forma": "tendrás",
    "traducción": "have",
    "contexto": "___ un examen la próxima semana."
  },
  {
    "infinitivo": "tener",
    "tiempo": "futuro",
    "sujeto": "él",
    "forma": "tendrá",
    "traducción": "has",
    "contexto": "___ una bicicleta nueva el próximo mes."
  },
  {
    "infinitivo": "tener",
    "tiempo": "futuro",
    "sujeto": "ella",
    "forma": "tendrá",
    "traducción": "has",
    "contexto": "___ una familia muy grande."
  },
  {
    "infinitivo": "tener",
    "tiempo": "futuro",
    "sujeto": "nosotros",
    "forma": "tendremos",
    "traducción": "have",
    "contexto": "___ una clase de español la próxima semana."
  },
  {
    "infinitivo": "tener",
    "tiempo": "futuro",
    "sujeto": "vosotros",
    "forma": "tendréis",
    "traducción": "have (en España)",
    "contexto": "¿___ mucho que estudiar para el examen de mañana? (España)"
  },
  {
    "infinitivo": "tener",
    "tiempo": "futuro",
    "sujeto": "ellos",
    "forma": "tendrán",
    "traducción": "have",
    "contexto": "___ tres perros en casa el próximo año."
  },
  {
    "infinitivo": "ser",
    "tiempo": "futuro",
    "sujeto": "yo",
    "forma": "seré",
    "traducción": "am",
    "contexto": "___ estudiante de español.",
    "tags": [
      "er",
      "irregular-all"
    ]
  },
  {
    "infinitivo": "ser",
    "tiempo": "futuro",
    "sujeto": "tú",
    "forma": "serás",
    "traducción": "are",
    "contexto": "___ muy simpático y divertido en el futuro."
  },
  {
    "infinitivo": "ser",
    "tiempo": "futuro",
    "sujeto": "él",
    "forma": "será",
    "traducción": "is",
    "contexto": "___ el hermano de mi mejor amigo."
  },
  {
    "infinitivo": "ser",
    "tiempo": "futuro",
    "sujeto": "ella",
    "forma": "será",
    "traducción": "is",
    "contexto": "___ muy creativa y curiosa."
  },
  {
    "infinitivo": "ser",
    "tiempo": "futuro",
    "sujeto": "nosotros",
    "forma": "seremos",
    "traducción": "are",
    "contexto": "___ parte de un equipo genial."
  },
  {
    "infinitivo": "ser",
    "tiempo": "futuro",
    "sujeto": "vosotros",
    "forma": "seréis",
    "traducción": "are (en España)",
    "contexto": "___ los mejores estudiantes de la clase. (España)"
  },
  {
    "infinitivo": "ser",
    "tiempo": "futuro",
    "sujeto": "ellos",
    "forma": "serán",
    "traducción": "are",
    "contexto": "___ mis compañeros de clase."
  },
  {
    "infinitivo": "estar",
    "tiempo": "futuro",
    "sujeto": "yo",
    "forma": "estaré",
    "traducción": "am",
    "contexto": "___ muy cansado mañana.",
    "tags": [
      "ar"
    ]
  },
  {
    "infinitivo": "estar",
    "tiempo": "futuro",
    "sujeto": "tú",
    "forma": "estarás",
    "traducción": "are",
    "contexto": "___ en la biblioteca más tarde."
  },
  {
    "infinitivo": "estar",
    "tiempo": "futuro",
    "sujeto": "él",
    "forma": "estará",
    "traducción": "is",
    "contexto": "___ enfermo y no podrá venir a clase."
  },
  {
    "infinitivo": "estar",
    "tiempo": "futuro",
    "sujeto": "ella",
    "forma": "estará",
    "traducción": "is",
    "contexto": "___ muy feliz con su nuevo trabajo."
  },
  {
    "infinitivo": "estar",
    "tiempo": "futuro",
    "sujeto": "nosotros",
    "forma": "estaremos",
    "traducción": "are",
    "contexto": "___ listos para empezar la semana."
  },
  {
    "infinitivo": "estar",
    "tiempo": "futuro",
    "sujeto": "vosotros",
    "forma": "estaréis",
    "traducción": "are (en España)",
    "contexto": "___ sentados en la primera fila. (España)"
  },
  {
    "infinitivo": "estar",
    "tiempo": "futuro",
    "sujeto": "ellos",
    "forma": "estarán",
    "traducción": "are",
    "contexto": "___ preocupados por el examen."
  },
  {
    "infinitivo": "hacer",
    "tiempo": "futuro",
    "sujeto": "yo",
    "forma": "haré",
    "traducción": "do",
    "contexto": "___ la tarea después de la cena.",
    "tags": [
      "cer",
      "er",
      "yo-irregular"
    ]
  },
  {
    "infinitivo": "hacer",
    "tiempo": "futuro",
    "sujeto": "tú",
    "forma": "harás",
    "traducción": "do",
    "contexto": "___ ejercicio en el gimnasio mañana."
  },
  {
    "infinitivo": "hacer",
    "tiempo": "futuro",
    "sujeto": "él",
    "forma": "hará",
    "traducción": "does",
    "contexto": "___ su cama todas las mañanas."
  },
  {
    "infinitivo": "hacer",
    "tiempo": "futuro",
    "sujeto": "ella",
    "forma": "hará",
    "traducción": "does",
    "contexto": "___ muchas preguntas en clase."
  },
  {
    "infinitivo": "hacer",
    "tiempo": "futuro",
    "sujeto": "nosotros",
    "forma": "haremos",
    "traducción": "do",
    "contexto": "___ un proyecto en grupo para la clase de ciencias."
  },
  {
    "infinitivo": "hacer",
    "tiempo": "futuro",
    "sujeto": "vosotros",
    "forma": "haréis",
    "traducción": "do (en España)",
    "contexto": "¿Qué ___ para ayudar en casa? (España)"
  },
  {
    "infinitivo": "hacer",
    "tiempo": "futuro",
    "sujeto": "ellos",
    "forma": "harán",
    "traducción": "do",
    "contexto": "___ muchas actividades extracurriculares."
  },
  {
    "infinitivo": "ir",
    "tiempo": "futuro",
    "sujeto": "yo",
    "forma": "iré",
    "traducción": "go",
    "contexto": "___ al supermercado mañana.",
    "tags": [
      "ir",
      "irregular-all"
    ]
  },
  {
    "infinitivo": "ir",
    "tiempo": "futuro",
    "sujeto": "tú",
    "forma": "irás",
    "traducción": "go",
    "contexto": "___ al cine con tus amigos."
  },
  {
    "infinitivo": "ir",
    "tiempo": "futuro",
    "sujeto": "él",
    "forma": "irá",
    "traducción": "goes",
    "contexto": "___ a la escuela en autobús."
  },
  {
    "infinitivo": "ir",
    "tiempo": "futuro",
    "sujeto": "ella",
    "forma": "irá",
    "traducción": "goes",
    "contexto": "___ al médico la próxima semana."
  },
  {
    "infinitivo": "ir",
    "tiempo": "futuro",
    "sujeto": "nosotros",
    "forma": "iremos",
    "traducción": "go",
    "contexto": "___ al parque después de clase."
  },
  {
    "infinitivo": "ir",
    "tiempo": "futuro",
    "sujeto": "vosotros",
    "forma": "iréis",
    "traducción": "go (en España)",
    "contexto": "¿A dónde ___ de vacaciones el próximo año? (España)"
  },
  {
    "infinitivo": "ir",
    "tiempo": "futuro",
    "sujeto": "ellos",
    "forma": "irán",
    "traducción": "go",
    "contexto": "___ al concierto el viernes por la noche."
  },
  {
    "infinitivo": "poder",
    "tiempo": "futuro",
    "sujeto": "yo",
    "forma": "podré",
    "traducción": "can",
    "contexto": "___ terminar el proyecto mañana.",
    "tags": [
      "er",
      "stem-change"
    ]
  },
  {
    "infinitivo": "poder",
    "tiempo": "futuro",
    "sujeto": "tú",
    "forma": "podrás",
    "traducción": "can",
    "contexto": "___ venir a mi casa esta tarde."
  },
  {
    "infinitivo": "poder",
    "tiempo": "futuro",
    "sujeto": "él",
    "forma": "podrá",
    "traducción": "can",
    "contexto": "___ jugar al fútbol muy bien."
  },
  {
    "infinitivo": "poder",
    "tiempo": "futuro",
    "sujeto": "ella",
    "forma": "podrá",
    "traducción": "can",
    "contexto": "___ ayudar con la tarea de matemáticas."
  },
  {
    "infinitivo": "poder",
    "tiempo": "futuro",
    "sujeto": "nosotros",
    "forma": "podremos",
    "traducción": "can",
    "contexto": "___ estudiar juntos para el examen."
  },
  {
    "infinitivo": "poder",
    "tiempo": "futuro",
    "sujeto": "vosotros",
    "forma": "podréis",
    "traducción": "can (en España)",
    "contexto": "¿___ escuchar la música desde aquí? (España)"
  },
  {
    "infinitivo": "poder",
    "tiempo": "futuro",
    "sujeto": "ellos",
    "forma": "podrán",
    "traducción": "can",
    "contexto": "___ correr cinco kilómetros sin parar."
  },
  {
    "infinitivo": "decir",
    "tiempo": "futuro",
    "sujeto": "yo",
    "forma": "diré",
    "traducción": "say",
    "contexto": "___ la verdad cuando alguien me pregunte.",
    "tags": [
      "cir",
      "ir",
      "stem-change",
      "yo-irregular"
    ]
  },
  {
    "infinitivo": "decir",
    "tiempo": "futuro",
    "sujeto": "tú",
    "forma": "dirás",
    "traducción": "say",
    "contexto": "___ cosas graciosas todo el tiempo."
  },
  {
    "infinitivo": "decir",
    "tiempo": "futuro",
    "sujeto": "él",
    "forma": "dirá",
    "traducción": "says",
    "contexto": "___ que no le gustará el chocolate."
  },
  {
    "infinitivo": "decir",
    "tiempo": "futuro",
    "sujeto": "ella",
    "forma": "dirá",
    "traducción": "says",
    "contexto": "___ que tendrá mucha tarea la próxima semana."
  },
  {
    "infinitivo": "decir",
    "tiempo": "futuro",
    "sujeto": "nosotros",
    "forma": "diremos",
    "traducción": "say",
    "contexto": "___ lo que pensamos en clase."
  },
  {
    "infinitivo": "decir",
    "tiempo": "futuro",
    "sujeto": "vosotros",
    "forma": "diréis",
    "traducción": "say (en España)",
    "contexto": "Siempre ___ la verdad, ¿verdad? (España)"
  },
  {
    "infinitivo": "decir",
    "tiempo": "futuro",
    "sujeto": "ellos",
    "forma": "dirán",
    "traducción": "say",
    "contexto": "___ que no querrán ir al cine."
  },
  {
    "infinitivo": "ver",
    "tiempo": "futuro",
    "sujeto": "yo",
    "forma": "veré",
    "traducción": "see",
    "contexto": "___ una película este fin de semana.",
    "tags": [
      "er",
      "yo-irregular"
    ]
  },
  {
    "infinitivo": "ver",
    "tiempo": "futuro",
    "sujeto": "tú",
    "forma": "verás",
    "traducción": "see",
    "contexto": "___ a tus amigos en la cafetería."
  },
  {
    "infinitivo": "ver",
    "tiempo": "futuro",
    "sujeto": "él",
    "forma": "verá",
    "traducción": "sees",
    "contexto": "___ la televisión después de cenar."
  },
  {
    "infinitivo": "ver",
    "tiempo": "futuro",
    "sujeto": "ella",
    "forma": "verá",
    "traducción": "sees",
    "contexto": "___ muchas series en su tiempo libre."
  },
  {
    "infinitivo": "ver",
    "tiempo": "futuro",
    "sujeto": "nosotros",
    "forma": "veremos",
    "traducción": "see",
    "contexto": "___ las estrellas cuando no haya nubes."
  },
  {
    "infinitivo": "ver",
    "tiempo": "futuro",
    "sujeto": "vosotros",
    "forma": "veréis",
    "traducción": "see (en España)",
    "contexto": "¿Qué ___ en la pantalla? (España)"
  },
  {
    "infinitivo": "ver",
    "tiempo": "futuro",
    "sujeto": "ellos",
    "forma": "verán",
    "traducción": "see",
    "contexto": "___ una obra de teatro juntos."
  },
  {
    "infinitivo": "dar",
    "tiempo": "futuro",
    "sujeto": "yo",
    "forma": "daré",
    "traducción": "give",
    "contexto": "___ muchos regalos en las fiestas.",
    "tags": [
      "ar",
      "yo-irregular"
    ]
  },
  {
    "infinitivo": "dar",
    "tiempo": "futuro",
    "sujeto": "tú",
    "forma": "darás",
    "traducción": "give",
    "contexto": "___ buenos consejos a tus amigos."
  },
  {
    "infinitivo": "dar",
    "tiempo": "futuro",
    "sujeto": "él",
    "forma": "dará",
    "traducción": "gives",
    "contexto": "___ clases en una universidad local."
  },
  {
    "infinitivo": "dar",
    "tiempo": "futuro",
    "sujeto": "ella",
    "forma": "dará",
    "traducción": "gives",
    "contexto": "___ su opinión en todas las reuniones."
  },
  {
    "infinitivo": "dar",
    "tiempo": "futuro",
    "sujeto": "nosotros",
    "forma": "daremos",
    "traducción": "give",
    "contexto": "___ un paseo por el parque el domingo."
  },
  {
    "infinitivo": "dar",
    "tiempo": "futuro",
    "sujeto": "vosotros",
    "forma": "daréis",
    "traducción": "give (en España)",
    "contexto": "___ siempre lo mejor de vosotros. (España)"
  },
  {
    "infinitivo": "dar",
    "tiempo": "futuro",
    "sujeto": "ellos",
    "forma": "darán",
    "traducción": "give",
    "contexto": "___ ayuda a quienes la necesiten."
  },
  {
    "infinitivo": "saber",
    "tiempo": "futuro",
    "sujeto": "yo",
    "forma": "sabré",
    "traducción": "know",
    "contexto": "___ la respuesta correcta.",
    "tags": [
      "er",
      "yo-irregular"
    ]
  },
  {
    "infinitivo": "saber",
    "tiempo": "futuro",
    "sujeto": "tú",
    "forma": "sabrás",
    "traducción": "know",
    "contexto": "___ mucho sobre historia."
  },
  {
    "infinitivo": "saber",
    "tiempo": "futuro",
    "sujeto": "él",
    "forma": "sabrá",
    "traducción": "knows",
    "contexto": "___ dónde estará el restaurante."
  },
  {
    "infinitivo": "saber",
    "tiempo": "futuro",
    "sujeto": "ella",
    "forma": "sabrá",
    "traducción": "knows",
    "contexto": "___ cómo tocar el piano."
  },
  {
    "infinitivo": "saber",
    "tiempo": "futuro",
    "sujeto": "nosotros",
    "forma": "sabremos",
    "traducción": "know",
    "contexto": "___ hablar tres idiomas."
  },
  {
    "infinitivo": "saber",
    "tiempo": "futuro",
    "sujeto": "vosotros",
    "forma": "sabréis",
    "traducción": "know (en España)",
    "contexto": "¿___ cómo llegar a la estación? (España)"
  },
  {
    "infinitivo": "saber",
    "tiempo": "futuro",
    "sujeto": "ellos",
    "forma": "sabrán",
    "traducción": "know",
    "contexto": "___ que tendrán que estudiar más."
  },
  {
    "infinitivo": "querer",
    "tiempo": "futuro",
    "sujeto": "yo",
    "forma": "querré",
    "traducción": "want",
    "contexto": "___ viajar a muchos países.",
    "tags": [
      "er",
      "stem-change"
    ]
  },
  {
    "infinitivo": "querer",
    "tiempo": "futuro",
    "sujeto": "tú",
    "forma": "querrás",
    "traducción": "want",
    "contexto": "___ comer pizza esta noche."
  },
  {
    "infinitivo": "querer",
    "tiempo": "futuro",
    "sujeto": "él",
    "forma": "querrá",
    "traducción": "wants",
    "contexto": "___ aprender a tocar la guitarra."
  },
  {
    "infinitivo": "querer",
    "tiempo": "futuro",
    "sujeto": "ella",
    "forma": "querrá",
    "traducción": "wants",
    "contexto": "___ ver una película de terror."
  },
  {
    "infinitivo": "querer",
    "tiempo": "futuro",
    "sujeto": "nosotros",
    "forma": "querremos",
    "traducción": "want",
    "contexto": "___ ir a la playa el próximo fin de semana."
  },
  {
    "infinitivo": "querer",
    "tiempo": "futuro",
    "sujeto": "vosotros",
    "forma": "querréis",
    "traducción": "want (en España)",
    "contexto": "¿Qué ___ cenar esta noche? (España)"
  },
  {
    "infinitivo": "querer",
    "tiempo": "futuro",
    "sujeto": "ellos",
    "forma": "querrán",
    "traducción": "want",
    "contexto": "___ jugar videojuegos después de la escuela."
  },
  {
    "infinitivo": "llegar",
    "tiempo": "futuro",
    "sujeto": "yo",
    "forma": "llegaré",
    "traducción": "arrive",
    "contexto": "___ temprano a la escuela mañana.",
    "tags": [
      "ar"
    ]
  },
  {
    "infinitivo": "llegar",
    "tiempo": "futuro",
    "sujeto": "tú",
    "forma": "llegarás",
    "traducción": "arrive",
    "contexto": "___ tarde al entrenamiento a veces."
  },
  {
    "infinitivo": "llegar",
    "tiempo": "futuro",
    "sujeto": "él",
    "forma": "llegará",
    "traducción": "arrives",
    "contexto": "___ justo a tiempo para la película."
  },
  {
    "infinitivo": "llegar",
    "tiempo": "futuro",
    "sujeto": "ella",
    "forma": "llegará",
    "traducción": "arrives",
    "contexto": "___ al aeropuerto con mucha anticipación."
  },
  {
    "infinitivo": "llegar",
    "tiempo": "futuro",
    "sujeto": "nosotros",
    "forma": "llegaremos",
    "traducción": "arrive",
    "contexto": "___ a la reunión cinco minutos antes."
  },
  {
    "infinitivo": "llegar",
    "tiempo": "futuro",
    "sujeto": "vosotros",
    "forma": "llegaréis",
    "traducción": "arrive (en España)",
    "contexto": "¿A qué hora ___ normalmente a casa? (España)"
  },
  {
    "infinitivo": "llegar",
    "tiempo": "futuro",
    "sujeto": "ellos",
    "forma": "llegarán",
    "traducción": "arrive",
    "contexto": "___ tarde a clase con frecuencia."
  },
  {
    "infinitivo": "pasar",
    "tiempo": "futuro",
    "sujeto": "yo",
    "forma": "pasaré",
    "traducción": "pass / spend (time)",
    "contexto": "___ mucho tiempo con mi familia el próximo fin de semana.",
    "tags": [
      "ar"
    ]
  },
  {
    "infinitivo": "pasar",
    "tiempo": "futuro",
    "sujeto": "tú",
    "forma": "pasarás",
    "traducción": "pass / you spend (time)",
    "contexto": "¿___ por el parque cuando vayas al trabajo?"
  },
  {
    "infinitivo": "pasar",
    "tiempo": "futuro",
    "sujeto": "él/ella/usted",
    "forma": "pasará",
    "traducción": "passes / spends (time)",
    "contexto": "___ todo el día estudiando para el examen."
  },
  {
    "infinitivo": "pasar",
    "tiempo": "futuro",
    "sujeto": "nosotros/nosotras",
    "forma": "pasaremos",
    "traducción": "pass / we spend (time)",
    "contexto": "___ las vacaciones en la playa."
  },
  {
    "infinitivo": "pasar",
    "tiempo": "futuro",
    "sujeto": "vosotros/vosotras",
    "forma": "pasaréis",
    "traducción": "pass / spend (time) (en España)",
    "contexto": "¿Cómo ___ el rato libre después de clase? (España)"
  },
  {
    "infinitivo": "pasar",
    "tiempo": "futuro",
    "sujeto": "ellos/ellas/ustedes",
    "forma": "pasarán",
    "traducción": "pass / spend (time)",
    "contexto": "___ muchas horas frente a la computadora."
  },
  {
    "infinitivo": "deber",
    "tiempo": "futuro",
    "sujeto": "yo",
    "forma": "deberé",
    "traducción": "should / must",
    "contexto": "___ estudiar para el examen de matemáticas.",
    "tags": [
      "er"
    ]
  },
  {
    "infinitivo": "deber",
    "tiempo": "futuro",
    "sujeto": "tú",
    "forma": "deberás",
    "traducción": "should / must",
    "contexto": "___ llamar a tu abuela hoy."
  },
  {
    "infinitivo": "deber",
    "tiempo": "futuro",
    "sujeto": "él / ella / usted",
    "forma": "deberá",
    "traducción": "should / must",
    "contexto": "___ terminar su proyecto esta semana."
  },
  {
    "infinitivo": "deber",
    "tiempo": "futuro",
    "sujeto": "nosotros / nosotras",
    "forma": "deberemos",
    "traducción": "should / must",
    "contexto": "___ practicar más para el torneo."
  },
  {
    "infinitivo": "deber",
    "tiempo": "futuro",
    "sujeto": "vosotros / vosotras",
    "forma": "deberéis",
    "traducción": "should / must (en España)",
    "contexto": "___ recordar traer los libros mañana. (España)"
  },
  {
    "infinitivo": "deber",
    "tiempo": "futuro",
    "sujeto": "ellos / ellas / ustedes",
    "forma": "deberán",
    "traducción": "should / must",
    "contexto": "___ llegar a tiempo a la reunión."
  },
  {
    "infinitivo": "poner",
    "tiempo": "futuro",
    "sujeto": "yo",
    "forma": "pondré",
    "traducción": "put",
    "contexto": "Siempre ___ las llaves en la mesa.",
    "tags": [
      "er",
      "yo-irregular"
    ]
  },
  {
    "infinitivo": "poner",
    "tiempo": "futuro",
    "sujeto": "tú",
    "forma": "pondrás",
    "traducción": "put",
    "contexto": "¿Dónde ___ tu mochila después de clase?"
  },
  {
    "infinitivo": "poner",
    "tiempo": "futuro",
    "sujeto": "él",
    "forma": "pondrá",
    "traducción": "puts",
    "contexto": "___ mucha atención en clase."
  },
  {
    "infinitivo": "poner",
    "tiempo": "futuro",
    "sujeto": "nosotros",
    "forma": "pondremos",
    "traducción": "put",
    "contexto": "___ la mesa antes de cenar."
  },
  {
    "infinitivo": "poner",
    "tiempo": "futuro",
    "sujeto": "vosotros",
    "forma": "pondréis",
    "traducción": "put (en España)",
    "contexto": "¿Dónde ___ los materiales de arte? (España)"
  },
  {
    "infinitivo": "poner",
    "tiempo": "futuro",
    "sujeto": "ellos",
    "forma": "pondrán",
    "traducción": "put",
    "contexto": "siempre ___ música en las fiestas."
  },
  {
    "infinitivo": "dejar",
    "tiempo": "futuro",
    "sujeto": "yo",
    "forma": "dejaré",
    "traducción": "leave / allow",
    "contexto": "___ mi mochila en casa mañana.",
    "tags": [
      "ar"
    ]
  },
  {
    "infinitivo": "dejar",
    "tiempo": "futuro",
    "sujeto": "tú",
    "forma": "dejarás",
    "traducción": "leave / allow",
    "contexto": "___ tus llaves en la mesa."
  },
  {
    "infinitivo": "dejar",
    "tiempo": "futuro",
    "sujeto": "él / ella / usted",
    "forma": "dejará",
    "traducción": "leaves / allows",
    "contexto": "___ que sus hijos vean televisión después de la cena."
  },
  {
    "infinitivo": "dejar",
    "tiempo": "futuro",
    "sujeto": "nosotros / nosotras",
    "forma": "dejaremos",
    "traducción": "leave / allow",
    "contexto": "___ los libros en el estante."
  },
  {
    "infinitivo": "dejar",
    "tiempo": "futuro",
    "sujeto": "vosotros / vosotras",
    "forma": "dejaréis",
    "traducción": "leave / allow (en España)",
    "contexto": "___ vuestros cuadernos encima de la mesa. (España)"
  },
  {
    "infinitivo": "dejar",
    "tiempo": "futuro",
    "sujeto": "ellos / ellas / ustedes",
    "forma": "dejarán",
    "traducción": "leave / allow",
    "contexto": " ___ sus zapatos en la entrada."
  },
  {
    "infinitivo": "llevar",
    "tiempo": "futuro",
    "sujeto": "yo",
    "forma": "llevaré",
    "traducción": "carry / wear",
    "contexto": "___ mi botella de agua al gimnasio.",
    "tags": [
      "ar"
    ]
  },
  {
    "infinitivo": "llevar",
    "tiempo": "futuro",
    "sujeto": "tú",
    "forma": "llevarás",
    "traducción": "carry / wear",
    "contexto": "___ siempre un suéter en la mochila."
  },
  {
    "infinitivo": "llevar",
    "tiempo": "futuro",
    "sujeto": "él / ella / usted",
    "forma": "llevará",
    "traducción": "carries / wears",
    "contexto": "___ gafas para leer."
  },
  {
    "infinitivo": "llevar",
    "tiempo": "futuro",
    "sujeto": "nosotros / nosotras",
    "forma": "llevaremos",
    "traducción": "carry / wear",
    "contexto": "___ todos los libros a la vez."
  },
  {
    "infinitivo": "llevar",
    "tiempo": "futuro",
    "sujeto": "vosotros / vosotras",
    "forma": "llevaréis",
    "traducción": "carry / wear (en España)",
    "contexto": "¿Cuánto tiempo ___ estudiando español? (España)"
  },
  {
    "infinitivo": "llevar",
    "tiempo": "futuro",
    "sujeto": "ellos / ellas / ustedes",
    "forma": "llevarán",
    "traducción": "carry / wear",
    "contexto": "___ sus propios audífonos para la clase."
  },
  {
    "infinitivo": "tomar",
    "tiempo": "futuro",
    "sujeto": "yo",
    "forma": "tomaré",
    "traducción": "take / drink",
    "contexto": "___ un vaso de agua antes de acostarme.",
    "tags": [
      "ar"
    ]
  },
  {
    "infinitivo": "tomar",
    "tiempo": "futuro",
    "sujeto": "tú",
    "forma": "tomarás",
    "traducción": "take / drink",
    "contexto": "___ el autobús para ir a la escuela."
  },
  {
    "infinitivo": "tomar",
    "tiempo": "futuro",
    "sujeto": "él / ella / usted",
    "forma": "tomará",
    "traducción": "takes / drinks",
    "contexto": "Siempre ___ café por la mañana."
  },
  {
    "infinitivo": "tomar",
    "tiempo": "futuro",
    "sujeto": "nosotros / nosotras",
    "forma": "tomaremos",
    "traducción": "take / drink",
    "contexto": "___ un descanso después de dos horas de estudio."
  },
  {
    "infinitivo": "tomar",
    "tiempo": "futuro",
    "sujeto": "vosotros / vosotras",
    "forma": "tomaréis",
    "traducción": "take / drink (en España)",
    "contexto": "¿Qué ___ para el dolor de cabeza? (España)"
  },
  {
    "infinitivo": "tomar",
    "tiempo": "futuro",
    "sujeto": "ellos / ellas / ustedes",
    "forma": "tomarán",
    "traducción": "take / drink",
    "contexto": "___ apuntes en clase para no olvidar nada."
  },
  {
    "infinitivo": "pensar",
    "tiempo": "futuro",
    "sujeto": "yo",
    "forma": "pensaré",
    "traducción": "think",
    "contexto": "___ que es una buena idea estudiar en grupo.",
    "tags": [
      "ar",
      "stem-change"
    ]
  },
  {
    "infinitivo": "pensar",
    "tiempo": "futuro",
    "sujeto": "tú",
    "forma": "pensarás",
    "traducción": "think",
    "contexto": "¿Qué ___ sobre el nuevo reglamento?"
  },
  {
    "infinitivo": "pensar",
    "tiempo": "futuro",
    "sujeto": "él / ella / usted",
    "forma": "pensará",
    "traducción": "thinks",
    "contexto": "___ mucho antes de tomar una decisión."
  },
  {
    "infinitivo": "pensar",
    "tiempo": "futuro",
    "sujeto": "nosotros / nosotras",
    "forma": "pensaremos",
    "traducción": "think",
    "contexto": "___ visitar ese museo durante el fin de semana."
  },
  {
    "infinitivo": "pensar",
    "tiempo": "futuro",
    "sujeto": "vosotros / vosotras",
    "forma": "pensaréis",
    "traducción": "think (en España)",
    "contexto": "¿Qué ___ de la nueva película? (España)"
  },
  {
    "infinitivo": "pensar",
    "tiempo": "futuro",
    "sujeto": "ellos / ellas / ustedes",
    "forma": "pensarán",
    "traducción": "think",
    "contexto": "___ que el examen va a ser difícil."
  },
  {
    "infinitivo": "entrar",
    "tiempo": "futuro",
    "sujeto": "yo",
    "forma": "entraré",
    "traducción": "enter",
    "contexto": "___ al salón de clase cinco minutos antes.",
    "tags": [
      "ar"
    ]
  },
  {
    "infinitivo": "entrar",
    "tiempo": "futuro",
    "sujeto": "tú",
    "forma": "entrarás",
    "traducción": "enter",
    "contexto": "¿A qué hora ___ al gimnasio?"
  },
  {
    "infinitivo": "entrar",
    "tiempo": "futuro",
    "sujeto": "él / ella / usted",
    "forma": "entrará",
    "traducción": "enters",
    "contexto": "___ al edificio por la puerta principal."
  },
  {
    "infinitivo": "entrar",
    "tiempo": "futuro",
    "sujeto": "nosotros / nosotras",
    "forma": "entraremos",
    "traducción": "enter",
    "contexto": "___ a la sala de reuniones a las 10 a.m."
  },
  {
    "infinitivo": "entrar",
    "tiempo": "futuro",
    "sujeto": "vosotros / vosotras",
    "forma": "entraréis",
    "traducción": "enter (en España)",
    "contexto": "___ al museo con la entrada anticipada. (España)"
  },
  {
    "infinitivo": "entrar",
    "tiempo": "futuro",
    "sujeto": "ellos / ellas / ustedes",
    "forma": "entrarán",
    "traducción": "enter",
    "contexto": "___ a la universidad para la graduación."
  },
  {
    "infinitivo": "mirar",
    "tiempo": "futuro",
    "sujeto": "yo",
    "forma": "miraré",
    "traducción": "watch / look at",
    "contexto": "___ una película en la televisión.",
    "tags": [
      "ar"
    ]
  },
  {
    "infinitivo": "mirar",
    "tiempo": "futuro",
    "sujeto": "tú",
    "forma": "mirarás",
    "traducción": "watch / look at",
    "contexto": "¿___ el marcador durante el partido?"
  },
  {
    "infinitivo": "mirar",
    "tiempo": "futuro",
    "sujeto": "él / ella / usted",
    "forma": "mirará",
    "traducción": "watches / looks at",
    "contexto": "___ las noticias de la tarde."
  },
  {
    "infinitivo": "mirar",
    "tiempo": "futuro",
    "sujeto": "nosotros / nosotras",
    "forma": "miraremos",
    "traducción": "watch / look at",
    "contexto": "___ las fotos de las vacaciones."
  },
  {
    "infinitivo": "mirar",
    "tiempo": "futuro",
    "sujeto": "vosotros / vosotras",
    "forma": "miraréis",
    "traducción": "watch / look at (en España)",
    "contexto": "___ la puesta de sol desde la playa. (España)"
  },
  {
    "infinitivo": "mirar",
    "tiempo": "futuro",
    "sujeto": "ellos / ellas / ustedes",
    "forma": "mirarán",
    "traducción": "watch / look at",
    "contexto": "___ el nuevo tráiler de la película."
  },
  {
    "infinitivo": "llamar",
    "tiempo": "futuro",
    "sujeto": "yo",
    "forma": "llamaré",
    "traducción": "call",
    "contexto": "___ a mi madre después de clase.",
    "tags": [
      "ar"
    ]
  },
  {
    "infinitivo": "llamar",
    "tiempo": "futuro",
    "sujeto": "tú",
    "forma": "llamarás",
    "traducción": "call",
    "contexto": "¿___ al doctor si no te sientes bien?"
  },
  {
    "infinitivo": "llamar",
    "tiempo": "futuro",
    "sujeto": "él / ella / usted",
    "forma": "llamará",
    "traducción": "calls",
    "contexto": "___ a su hermano para saludarlo."
  },
  {
    "infinitivo": "llamar",
    "tiempo": "futuro",
    "sujeto": "nosotros / nosotras",
    "forma": "llamaremos",
    "traducción": "call",
    "contexto": "___ a la policía si hay un problema."
  },
  {
    "infinitivo": "llamar",
    "tiempo": "futuro",
    "sujeto": "vosotros / vosotras",
    "forma": "llamaréis",
    "traducción": "call (en España)",
    "contexto": "¿A quién ___ para pedir ayuda? (España)"
  },
  {
    "infinitivo": "llamar",
    "tiempo": "futuro",
    "sujeto": "ellos / ellas / ustedes",
    "forma": "llamarán",
    "traducción": "call",
    "contexto": "___ al restaurante para hacer una reserva."
  },
  {
    "infinitivo": "llamarse",
    "tiempo": "futuro",
    "sujeto": "yo",
    "forma": "me llamaré",
    "traducción": "am called",
    "contexto": "___ Juan el próximo año.",
    "tags": [
      "ar",
      "reflexive"
    ]
  },
  {
    "infinitivo": "llamarse",
    "tiempo": "futuro",
    "sujeto": "tú",
    "forma": "te llamarás",
    "traducción": "are called",
    "contexto": "¿Cómo ___ cuando seas famoso?"
  },
  {
    "infinitivo": "llamarse",
    "tiempo": "futuro",
    "sujeto": "él",
    "forma": "se llamará",
    "traducción": "is called",
    "contexto": "Su equipo ___ el equipo de los leones."
  },
  {
    "infinitivo": "llamarse",
    "tiempo": "futuro",
    "sujeto": "nosotros",
    "forma": "nos llamaremos",
    "traducción": "are called",
    "contexto": "___ por nuestro nombre."
  },
  {
    "infinitivo": "llamarse",
    "tiempo": "futuro",
    "sujeto": "vosotros",
    "forma": "os llamaréis",
    "traducción": "are called (en España)",
    "contexto": "¿Cómo ___ vuestros padres? (España)"
  },
  {
    "infinitivo": "llamarse",
    "tiempo": "futuro",
    "sujeto": "ellos",
    "forma": "se llamarán",
    "traducción": "are called",
    "contexto": "Mis amigos ___ Ana y Carlos."
  },
  {
    "infinitivo": "necesitar",
    "tiempo": "futuro",
    "sujeto": "yo",
    "forma": "necesitaré",
    "traducción": "need",
    "contexto": "___ ayuda para mover esta caja.",
    "tags": [
      "ar"
    ]
  },
  {
    "infinitivo": "necesitar",
    "tiempo": "futuro",
    "sujeto": "tú",
    "forma": "necesitarás",
    "traducción": "need",
    "contexto": "¿___ algo para la clase de mañana?"
  },
  {
    "infinitivo": "necesitar",
    "tiempo": "futuro",
    "sujeto": "él",
    "forma": "necesitará",
    "traducción": "needs",
    "contexto": "___ un bolígrafo para escribir."
  },
  {
    "infinitivo": "necesitar",
    "tiempo": "futuro",
    "sujeto": "nosotros",
    "forma": "necesitaremos",
    "traducción": "need",
    "contexto": "___ más tiempo para completar la tarea."
  },
  {
    "infinitivo": "necesitar",
    "tiempo": "futuro",
    "sujeto": "vosotros",
    "forma": "necesitaréis",
    "traducción": "need (en España)",
    "contexto": "___ un descanso después de tanto estudiar. (España)"
  },
  {
    "infinitivo": "necesitar",
    "tiempo": "futuro",
    "sujeto": "ellos",
    "forma": "necesitarán",
    "traducción": "need",
    "contexto": "___ mucha práctica para el examen."
  },
  {
    "infinitivo": "parecer",
    "tiempo": "futuro",
    "sujeto": "yo",
    "forma": "pareceré",
    "traducción": "seem / look",
    "contexto": "___ más alto el próximo año.",
    "tags": [
      "er",
      "yo-irregular"
    ]
  },
  {
    "infinitivo": "parecer",
    "tiempo": "futuro",
    "sujeto": "tú",
    "forma": "parecerás",
    "traducción": "seem / look",
    "contexto": "___ cansado si no duermes bien."
  },
  {
    "infinitivo": "parecer",
    "tiempo": "futuro",
    "sujeto": "él / ella / usted",
    "forma": "parecerá",
    "traducción": "seems / looks",
    "contexto": "El proyecto ___ fácil de terminar."
  },
  {
    "infinitivo": "parecer",
    "tiempo": "futuro",
    "sujeto": "nosotros / nosotras",
    "forma": "pareceremos",
    "traducción": "seem / look",
    "contexto": "___ más jóvenes cuando nos cortemos el pelo."
  },
  {
    "infinitivo": "parecer",
    "tiempo": "futuro",
    "sujeto": "vosotros / vosotras",
    "forma": "pareceréis",
    "traducción": "seem / look (en España)",
    "contexto": "___ sorprendidos por la noticia. (España)"
  },
  {
    "infinitivo": "parecer",
    "tiempo": "futuro",
    "sujeto": "ellos / ellas / ustedes",
    "forma": "parecerán",
    "traducción": "seem / look",
    "contexto": "Los problemas ___ más grandes de lo que son."
  },
  {
    "infinitivo": "regresar",
    "tiempo": "futuro",
    "sujeto": "yo",
    "forma": "regresaré",
    "traducción": "return / go back",
    "contexto": "___ a casa después del trabajo.",
    "tags": [
      "ar"
    ]
  },
  {
    "infinitivo": "regresar",
    "tiempo": "futuro",
    "sujeto": "tú",
    "forma": "regresarás",
    "traducción": "return / go back",
    "contexto": "¿A qué hora ___ de la excursión?"
  },
  {
    "infinitivo": "regresar",
    "tiempo": "futuro",
    "sujeto": "él",
    "forma": "regresará",
    "traducción": "returns / goes back",
    "contexto": "___ de su viaje la próxima semana."
  },
  {
    "infinitivo": "regresar",
    "tiempo": "futuro",
    "sujeto": "nosotros",
    "forma": "regresaremos",
    "traducción": "return / go back",
    "contexto": "___ al mismo hotel el próximo año."
  },
  {
    "infinitivo": "regresar",
    "tiempo": "futuro",
    "sujeto": "vosotros",
    "forma": "regresaréis",
    "traducción": "return / go back (en España)",
    "contexto": "¿Cuándo ___ de las vacaciones? (España)"
  },
  {
    "infinitivo": "regresar",
    "tiempo": "futuro",
    "sujeto": "ellos",
    "forma": "regresarán",
    "traducción": "return / go back",
    "contexto": "___ al trabajo después de una pausa."
  },
  {
    "infinitivo": "abrir",
    "tiempo": "futuro",
    "sujeto": "yo",
    "forma": "abriré",
    "traducción": "open",
    "contexto": "___ un regalo de cumpleaños.",
    "tags": [
      "ir"
    ]
  },
  {
    "infinitivo": "abrir",
    "tiempo": "futuro",
    "sujeto": "tú",
    "forma": "abrirás",
    "traducción": "open",
    "contexto": "___ la ventana cuando haga calor."
  },
  {
    "infinitivo": "abrir",
    "tiempo": "futuro",
    "sujeto": "él / ella / usted",
    "forma": "abrirá",
    "traducción": "opens",
    "contexto": "La tienda ___ a las nueve mañana."
  },
  {
    "infinitivo": "abrir",
    "tiempo": "futuro",
    "sujeto": "nosotros / nosotras",
    "forma": "abriremos",
    "traducción": "open",
    "contexto": "___ la puerta a los invitados."
  },
  {
    "infinitivo": "abrir",
    "tiempo": "futuro",
    "sujeto": "vosotros / vosotras",
    "forma": "abriréis",
    "traducción": "open (en España)",
    "contexto": "¿Cuándo ___ vuestro propio negocio? (España)"
  },
  {
    "infinitivo": "abrir",
    "tiempo": "futuro",
    "sujeto": "ellos / ellas / ustedes",
    "forma": "abrirán",
    "traducción": "open",
    "contexto": "___ sus regalos de Navidad."
  },
  {
    "infinitivo": "andar",
    "tiempo": "futuro",
    "sujeto": "yo",
    "forma": "andaré",
    "traducción": "walk / stroll",
    "contexto": "___ por el parque esta tarde.",
    "tags": [
      "ar"
    ]
  },
  {
    "infinitivo": "andar",
    "tiempo": "futuro",
    "sujeto": "tú",
    "forma": "andarás",
    "traducción": "walk / stroll",
    "contexto": "¿___ bien después de la lesión?"
  },
  {
    "infinitivo": "andar",
    "tiempo": "futuro",
    "sujeto": "él / ella / usted",
    "forma": "andará",
    "traducción": "walks / strolls",
    "contexto": "Mi abuelo ___ con bastón."
  },
  {
    "infinitivo": "andar",
    "tiempo": "futuro",
    "sujeto": "nosotros / nosotras",
    "forma": "andaremos",
    "traducción": "walk / stroll",
    "contexto": "___ rápido para llegar antes."
  },
  {
    "infinitivo": "andar",
    "tiempo": "futuro",
    "sujeto": "vosotros / vosotras",
    "forma": "andaréis",
    "traducción": "walk / stroll (en España)",
    "contexto": "¿Por qué ___ tan callados hoy? (España)"
  },
  {
    "infinitivo": "andar",
    "tiempo": "futuro",
    "sujeto": "ellos / ellas / ustedes",
    "forma": "andarán",
    "traducción": "walk / stroll",
    "contexto": "___ por el campo buscando flores."
  },
  {
    "infinitivo": "encontrar",
    "tiempo": "futuro",
    "sujeto": "yo",
    "forma": "encontraré",
    "traducción": "find",
    "contexto": "___ mi libro debajo de la cama.",
    "tags": [
      "ar",
      "stem-change"
    ]
  },
  {
    "infinitivo": "encontrar",
    "tiempo": "futuro",
    "sujeto": "tú",
    "forma": "encontrarás",
    "traducción": "find",
    "contexto": "¿___ el error en la ecuación?"
  },
  {
    "infinitivo": "encontrar",
    "tiempo": "futuro",
    "sujeto": "él / ella / usted",
    "forma": "encontrará",
    "traducción": "finds",
    "contexto": "Mi primo ___ tiempo para todos sus hobbies."
  },
  {
    "infinitivo": "encontrar",
    "tiempo": "futuro",
    "sujeto": "nosotros / nosotras",
    "forma": "encontraremos",
    "traducción": "find",
    "contexto": "___ una solución al problema."
  },
  {
    "infinitivo": "encontrar",
    "tiempo": "futuro",
    "sujeto": "vosotros / vosotras",
    "forma": "encontraréis",
    "traducción": "find (en España)",
    "contexto": "___ lo que buscáis en internet. (España)"
  },
  {
    "infinitivo": "encontrar",
    "tiempo": "futuro",
    "sujeto": "ellos / ellas / ustedes",
    "forma": "encontrarán",
    "traducción": "find",
    "contexto": "___ un buen lugar para cenar."
  },
  {
    "infinitivo": "conocer",
    "tiempo": "futuro",
    "sujeto": "yo",
    "forma": "conoceré",
    "traducción": "know / be familiar with",
    "contexto": "___ un nuevo restaurante el fin de semana.",
    "tags": [
      "er",
      "yo-irregular"
    ]
  },
  {
    "infinitivo": "conocer",
    "tiempo": "futuro",
    "sujeto": "tú",
    "forma": "conocerás",
    "traducción": "know / be familiar with",
    "contexto": "___ a todos los profesores del departamento."
  },
  {
    "infinitivo": "conocer",
    "tiempo": "futuro",
    "sujeto": "él",
    "forma": "conocerá",
    "traducción": "knows / is familiar with",
    "contexto": "___ muy bien la cultura española."
  },
  {
    "infinitivo": "conocer",
    "tiempo": "futuro",
    "sujeto": "nosotros",
    "forma": "conoceremos",
    "traducción": "know / be familiar with",
    "contexto": "___ un buen lugar para comer."
  },
  {
    "infinitivo": "conocer",
    "tiempo": "futuro",
    "sujeto": "vosotros",
    "forma": "conoceréis",
    "traducción": "know / be familiar with (en España)",
    "contexto": "¿___ a alguien de esa universidad? (España)"
  },
  {
    "infinitivo": "conocer",
    "tiempo": "futuro",
    "sujeto": "ellos",
    "forma": "conocerán",
    "traducción": "know / be familiar with",
    "contexto": "___ a muchos artistas locales."
  },
  {
    "infinitivo": "vivir",
    "tiempo": "futuro",
    "sujeto": "yo",
    "forma": "viviré",
    "traducción": "live",
    "contexto": "___ en un apartamento pequeño en el centro.",
    "tags": [
      "ir"
    ]
  },
  {
    "infinitivo": "vivir",
    "tiempo": "futuro",
    "sujeto": "tú",
    "forma": "vivirás",
    "traducción": "live",
    "contexto": "¿Dónde ___ con tu familia?"
  },
  {
    "infinitivo": "vivir",
    "tiempo": "futuro",
    "sujeto": "él",
    "forma": "vivirá",
    "traducción": "lives",
    "contexto": "___ solo en una casa grande."
  },
  {
    "infinitivo": "vivir",
    "tiempo": "futuro",
    "sujeto": "ella",
    "forma": "vivirá",
    "traducción": "lives",
    "contexto": "___ cerca de su trabajo."
  },
  {
    "infinitivo": "vivir",
    "tiempo": "futuro",
    "sujeto": "nosotros",
    "forma": "viviremos",
    "traducción": "live",
    "contexto": "___ en el mismo edificio."
  },
  {
    "infinitivo": "vivir",
    "tiempo": "futuro",
    "sujeto": "vosotros",
    "forma": "viviréis",
    "traducción": "live (en España)",
    "contexto": "___ juntos en una casa grande. (España)"
  },
  {
    "infinitivo": "vivir",
    "tiempo": "futuro",
    "sujeto": "ellos",
    "forma": "vivirán",
    "traducción": "live",
    "contexto": "___ en un país diferente el próximo año."
  },
  {
    "infinitivo": "dormir",
    "tiempo": "futuro",
    "sujeto": "yo",
    "forma": "dormiré",
    "traducción": "sleep",
    "contexto": "___ ocho horas mañana por la noche.",
    "tags": [
      "ir",
      "stem-change"
    ]
  },
  {
    "infinitivo": "dormir",
    "tiempo": "futuro",
    "sujeto": "tú",
    "forma": "dormirás",
    "traducción": "sleep",
    "contexto": "¿___ bien antes de un examen?"
  },
  {
    "infinitivo": "dormir",
    "tiempo": "futuro",
    "sujeto": "él / ella / usted",
    "forma": "dormirá",
    "traducción": "sleeps",
    "contexto": "Mi gato ___ todo el día."
  },
  {
    "infinitivo": "dormir",
    "tiempo": "futuro",
    "sujeto": "nosotros / nosotras",
    "forma": "dormiremos",
    "traducción": "sleep",
    "contexto": "___ en un hotel con vistas al mar."
  },
  {
    "infinitivo": "dormir",
    "tiempo": "futuro",
    "sujeto": "vosotros / vosotras",
    "forma": "dormiréis",
    "traducción": "sleep (en España)",
    "contexto": "___ en tiendas de campaña este fin de semana. (España)"
  },
  {
    "infinitivo": "dormir",
    "tiempo": "futuro",
    "sujeto": "ellos / ellas / ustedes",
    "forma": "dormirán",
    "traducción": "sleep",
    "contexto": "___ después de un largo día de trabajo."
  },
  {
    "infinitivo": "salir",
    "tiempo": "futuro",
    "sujeto": "yo",
    "forma": "saldré",
    "traducción": "go out / leave",
    "contexto": "___ del trabajo a las cinco hoy.",
    "tags": [
      "ir",
      "yo-irregular"
    ]
  },
  {
    "infinitivo": "salir",
    "tiempo": "futuro",
    "sujeto": "tú",
    "forma": "saldrás",
    "traducción": "go out / leave",
    "contexto": "___ con tus amigos el viernes."
  },
  {
    "infinitivo": "salir",
    "tiempo": "futuro",
    "sujeto": "él / ella / usted",
    "forma": "saldrá",
    "traducción": "goes out / leaves",
    "contexto": "El sol ___ pronto."
  },
  {
    "infinitivo": "salir",
    "tiempo": "futuro",
    "sujeto": "nosotros / nosotras",
    "forma": "saldremos",
    "traducción": "go out / leave",
    "contexto": "___ de viaje este verano."
  },
  {
    "infinitivo": "salir",
    "tiempo": "futuro",
    "sujeto": "vosotros / vosotras",
    "forma": "saldréis",
    "traducción": "go out / leave (en España)",
    "contexto": "¿A qué hora ___ para la fiesta? (España)"
  },
  {
    "infinitivo": "salir",
    "tiempo": "futuro",
    "sujeto": "ellos / ellas / ustedes",
    "forma": "saldrán",
    "traducción": "go out / leave",
    "contexto": "___ de la reunión a tiempo."
  },
  {
    "infinitivo": "existir",
    "tiempo": "futuro",
    "sujeto": "yo",
    "forma": "existiré",
    "traducción": "exist",
    "contexto": "___ en este mundo por una razón.",
    "tags": [
      "ir"
    ]
  },
  {
    "infinitivo": "existir",
    "tiempo": "futuro",
    "sujeto": "tú",
    "forma": "existirás",
    "traducción": "exist",
    "contexto": "___ como persona independiente."
  },
  {
    "infinitivo": "existir",
    "tiempo": "futuro",
    "sujeto": "él / ella / usted",
    "forma": "existirá",
    "traducción": "exists",
    "contexto": "El problema ___ hasta que se resuelva."
  },
  {
    "infinitivo": "existir",
    "tiempo": "futuro",
    "sujeto": "nosotros / nosotras",
    "forma": "existiremos",
    "traducción": "exist",
    "contexto": "___ como grupo de estudio."
  },
  {
    "infinitivo": "existir",
    "tiempo": "futuro",
    "sujeto": "vosotros / vosotras",
    "forma": "existiréis",
    "traducción": "exist (en España)",
    "contexto": "¿De verdad ___ solo para estudiar y trabajar? (España)"
  },
  {
    "infinitivo": "existir",
    "tiempo": "futuro",
    "sujeto": "ellos / ellas / ustedes",
    "forma": "existirán",
    "traducción": "exist",
    "contexto": "___ muchas razones para estar feliz."
  },
  {
    "infinitivo": "usar",
    "tiempo": "futuro",
    "sujeto": "yo",
    "forma": "usaré",
    "traducción": "use",
    "contexto": "___ una aplicación de notas para hacer tarea.",
    "tags": [
      "ar"
    ]
  },
  {
    "infinitivo": "usar",
    "tiempo": "futuro",
    "sujeto": "tú",
    "forma": "usarás",
    "traducción": "use",
    "contexto": "¿___ esa aplicación nueva?"
  },
  {
    "infinitivo": "usar",
    "tiempo": "futuro",
    "sujeto": "él/ella",
    "forma": "usará",
    "traducción": "uses",
    "contexto": "Ella ___ lentes para leer."
  },
  {
    "infinitivo": "usar",
    "tiempo": "futuro",
    "sujeto": "nosotros",
    "forma": "usaremos",
    "traducción": "use",
    "contexto": "___ diccionarios digitales en clase."
  },
  {
    "infinitivo": "usar",
    "tiempo": "futuro",
    "sujeto": "vosotros",
    "forma": "usaréis",
    "traducción": "use (en España)",
    "contexto": "¿___ un mapa para orientaros en la ciudad? (España)"
  },
  {
    "infinitivo": "usar",
    "tiempo": "futuro",
    "sujeto": "ellos",
    "forma": "usarán",
    "traducción": "use",
    "contexto": "Ellos ___ ropa cómoda en casa."
  },
  {
    "infinitivo": "empezar",
    "tiempo": "futuro",
    "sujeto": "yo",
    "forma": "empezaré",
    "traducción": "begin / start",
    "contexto": "___ a trabajar temprano mañana.",
    "tags": [
      "ar",
      "stem-change"
    ]
  },
  {
    "infinitivo": "empezar",
    "tiempo": "futuro",
    "sujeto": "tú",
    "forma": "empezarás",
    "traducción": "begin / start",
    "contexto": "¿A qué hora ___ a estudiar hoy?"
  },
  {
    "infinitivo": "empezar",
    "tiempo": "futuro",
    "sujeto": "él / ella / usted",
    "forma": "empezará",
    "traducción": "begins / starts",
    "contexto": "La película ___ en cinco minutos."
  },
  {
    "infinitivo": "empezar",
    "tiempo": "futuro",
    "sujeto": "nosotros / nosotras",
    "forma": "empezaremos",
    "traducción": "begin / start",
    "contexto": "___ el proyecto después de la reunión."
  },
  {
    "infinitivo": "empezar",
    "tiempo": "futuro",
    "sujeto": "vosotros / vosotras",
    "forma": "empezaréis",
    "traducción": "begin / start (en España)",
    "contexto": "¿Cuándo ___ el curso de cocina? (España)"
  },
  {
    "infinitivo": "empezar",
    "tiempo": "futuro",
    "sujeto": "ellos / ellas / ustedes",
    "forma": "empezarán",
    "traducción": "begin / start",
    "contexto": "___ un nuevo negocio."
  },
  {
    "infinitivo": "cambiar",
    "tiempo": "futuro",
    "sujeto": "yo",
    "forma": "cambiaré",
    "traducción": "change",
    "contexto": "___ de opinión si es necesario.",
    "tags": [
      "ar"
    ]
  },
  {
    "infinitivo": "cambiar",
    "tiempo": "futuro",
    "sujeto": "tú",
    "forma": "cambiarás",
    "traducción": "change",
    "contexto": "___ tu horario de clases."
  },
  {
    "infinitivo": "cambiar",
    "tiempo": "futuro",
    "sujeto": "él / ella / usted",
    "forma": "cambiará",
    "traducción": "changes",
    "contexto": "Mi hermano ___ de universidad el próximo año."
  },
  {
    "infinitivo": "cambiar",
    "tiempo": "futuro",
    "sujeto": "nosotros / nosotras",
    "forma": "cambiaremos",
    "traducción": "change",
    "contexto": "___ el horario de la reunión."
  },
  {
    "infinitivo": "cambiar",
    "tiempo": "futuro",
    "sujeto": "vosotros / vosotras",
    "forma": "cambiaréis",
    "traducción": "change (en España)",
    "contexto": "¿___ vuestros planes por la lluvia? (España)"
  },
  {
    "infinitivo": "cambiar",
    "tiempo": "futuro",
    "sujeto": "ellos / ellas / ustedes",
    "forma": "cambiarán",
    "traducción": "change",
    "contexto": "___ de tema de conversación rápidamente."
  },
  {
    "infinitivo": "creer",
    "tiempo": "futuro",
    "sujeto": "yo",
    "forma": "creeré",
    "traducción": "believe",
    "contexto": "___ que el examen será fácil.",
    "tags": [
      "er"
    ]
  },
  {
    "infinitivo": "creer",
    "tiempo": "futuro",
    "sujeto": "tú",
    "forma": "creerás",
    "traducción": "believe",
    "contexto": "¿___ en los fantasmas?"
  },
  {
    "infinitivo": "creer",
    "tiempo": "futuro",
    "sujeto": "él / ella / usted",
    "forma": "creerá",
    "traducción": "believes",
    "contexto": "Mi amigo ___ todo lo que le diga."
  },
  {
    "infinitivo": "creer",
    "tiempo": "futuro",
    "sujeto": "nosotros / nosotras",
    "forma": "creeremos",
    "traducción": "believe",
    "contexto": "___ que es importante ser honestos."
  },
  {
    "infinitivo": "creer",
    "tiempo": "futuro",
    "sujeto": "vosotros / vosotras",
    "forma": "creeréis",
    "traducción": "believe (en España)",
    "contexto": "___ en vuestra capacidad para ganar. (España)"
  },
  {
    "infinitivo": "creer",
    "tiempo": "futuro",
    "sujeto": "ellos / ellas / ustedes",
    "forma": "creerán",
    "traducción": "believe",
    "contexto": "___ en la importancia de la educación."
  },
  {
    "infinitivo": "contar",
    "tiempo": "futuro",
    "sujeto": "yo",
    "forma": "contaré",
    "traducción": "count / tell",
    "contexto": "___ hasta diez antes de responder.",
    "tags": [
      "ar",
      "stem-change"
    ]
  },
  {
    "infinitivo": "contar",
    "tiempo": "futuro",
    "sujeto": "tú",
    "forma": "contarás",
    "traducción": "count / tell",
    "contexto": "___ una historia interesante."
  },
  {
    "infinitivo": "contar",
    "tiempo": "futuro",
    "sujeto": "él / ella / usted",
    "forma": "contará",
    "traducción": "counts / tells",
    "contexto": "___ con el apoyo de sus amigos."
  },
  {
    "infinitivo": "contar",
    "tiempo": "futuro",
    "sujeto": "nosotros / nosotras",
    "forma": "contaremos",
    "traducción": "count / tell",
    "contexto": "___ con los dedos para sumar."
  },
  {
    "infinitivo": "contar",
    "tiempo": "futuro",
    "sujeto": "vosotros / vosotras",
    "forma": "contaréis",
    "traducción": "count / tell (en España)",
    "contexto": "___ la verdad sobre lo que pasó. (España)"
  },
  {
    "infinitivo": "contar",
    "tiempo": "futuro",
    "sujeto": "ellos / ellas / ustedes",
    "forma": "contarán",
    "traducción": "count / tell",
    "contexto": "___ hasta cien para relajarse."
  },
  {
    "infinitivo": "entender",
    "tiempo": "futuro",
    "sujeto": "yo",
    "forma": "entenderé",
    "traducción": "understand",
    "contexto": "___ la gramática española mejor que antes.",
    "tags": [
      "er",
      "stem-change"
    ]
  },
  {
    "infinitivo": "entender",
    "tiempo": "futuro",
    "sujeto": "tú",
    "forma": "entenderás",
    "traducción": "understand",
    "contexto": "¿___ lo que dice el locutor de radio?"
  },
  {
    "infinitivo": "entender",
    "tiempo": "futuro",
    "sujeto": "él / ella / usted",
    "forma": "entenderá",
    "traducción": "understands",
    "contexto": "Mi hermana no ___ por qué estaremos aquí."
  },
  {
    "infinitivo": "entender",
    "tiempo": "futuro",
    "sujeto": "nosotros / nosotras",
    "forma": "entenderemos",
    "traducción": "understand",
    "contexto": "___ que el ejercicio es importante para la salud."
  },
  {
    "infinitivo": "entender",
    "tiempo": "futuro",
    "sujeto": "vosotros / vosotras",
    "forma": "entenderéis",
    "traducción": "understand (en España)",
    "contexto": "¿___ bien la nueva lección? (España)"
  },
  {
    "infinitivo": "entender",
    "tiempo": "futuro",
    "sujeto": "ellos / ellas / ustedes",
    "forma": "entenderán",
    "traducción": "understand",
    "contexto": "___ la complejidad del problema."
  },
  {
    "infinitivo": "sacar",
    "tiempo": "futuro",
    "sujeto": "yo",
    "forma": "sacaré",
    "traducción": "take out / get (grades)",
    "contexto": "___ muy buenas notas en la mayoría de las materias.",
    "tags": [
      "ar"
    ]
  },
  {
    "infinitivo": "sacar",
    "tiempo": "futuro",
    "sujeto": "tú",
    "forma": "sacarás",
    "traducción": "take out / get (grades)",
    "contexto": "___ la basura antes de que llueva."
  },
  {
    "infinitivo": "sacar",
    "tiempo": "futuro",
    "sujeto": "él / ella / usted",
    "forma": "sacará",
    "traducción": "takes out / gets (grades)",
    "contexto": "Mi amigo ___ el coche del garaje."
  },
  {
    "infinitivo": "sacar",
    "tiempo": "futuro",
    "sujeto": "nosotros / nosotras",
    "forma": "sacaremos",
    "traducción": "take out / get (grades)",
    "contexto": "___ una foto del grupo."
  },
  {
    "infinitivo": "sacar",
    "tiempo": "futuro",
    "sujeto": "vosotros / vosotras",
    "forma": "sacaréis",
    "traducción": "take out / get (grades) (en España)",
    "contexto": "___ los billetes para el tren. (España)"
  },
  {
    "infinitivo": "sacar",
    "tiempo": "futuro",
    "sujeto": "ellos / ellas / ustedes",
    "forma": "sacarán",
    "traducción": "take out / get (grades)",
    "contexto": "___ sus conclusiones después de leer el informe."
  },
  {
    "infinitivo": "escuchar",
    "tiempo": "futuro",
    "sujeto": "yo",
    "forma": "escucharé",
    "traducción": "listen to",
    "contexto": "___ mi música favorita esta noche.",
    "tags": [
      "ar"
    ]
  },
  {
    "infinitivo": "escuchar",
    "tiempo": "futuro",
    "sujeto": "tú",
    "forma": "escucharás",
    "traducción": "listen to",
    "contexto": "___ a tus profesores en clase."
  },
  {
    "infinitivo": "escuchar",
    "tiempo": "futuro",
    "sujeto": "él / ella / usted",
    "forma": "escuchará",
    "traducción": "listens to",
    "contexto": "Mi padre ___ la radio por las mañanas."
  },
  {
    "infinitivo": "escuchar",
    "tiempo": "futuro",
    "sujeto": "nosotros / nosotras",
    "forma": "escucharemos",
    "traducción": "listen to",
    "contexto": "___ las noticias todos los días."
  },
  {
    "infinitivo": "escuchar",
    "tiempo": "futuro",
    "sujeto": "vosotros / vosotras",
    "forma": "escucharéis",
    "traducción": "listen to (en España)",
    "contexto": "¿___ atentamente las instrucciones? (España)"
  },
  {
    "infinitivo": "escuchar",
    "tiempo": "futuro",
    "sujeto": "ellos / ellas / ustedes",
    "forma": "escucharán",
    "traducción": "listen to",
    "contexto": "___ un podcast sobre historia."
  },
  {
    "infinitivo": "perder",
    "tiempo": "futuro",
    "sujeto": "yo",
    "forma": "perderé",
    "traducción": "lose",
    "contexto": "A veces ___ mis llaves.",
    "tags": [
      "er",
      "stem-change"
    ]
  },
  {
    "infinitivo": "perder",
    "tiempo": "futuro",
    "sujeto": "tú",
    "forma": "perderás",
    "traducción": "lose",
    "contexto": "¿___ mucho tiempo en redes sociales?"
  },
  {
    "infinitivo": "perder",
    "tiempo": "futuro",
    "sujeto": "él / ella / usted",
    "forma": "perderá",
    "traducción": "loses",
    "contexto": "Mi equipo ___ los partidos importantes."
  },
  {
    "infinitivo": "perder",
    "tiempo": "futuro",
    "sujeto": "nosotros / nosotras",
    "forma": "perderemos",
    "traducción": "lose",
    "contexto": "___ el autobús si no nos damos prisa."
  },
  {
    "infinitivo": "perder",
    "tiempo": "futuro",
    "sujeto": "vosotros / vosotras",
    "forma": "perderéis",
    "traducción": "lose (en España)",
    "contexto": "___ vuestros billetes si no tenéis cuidado. (España)"
  },
  {
    "infinitivo": "perder",
    "tiempo": "futuro",
    "sujeto": "ellos / ellas / ustedes",
    "forma": "perderán",
    "traducción": "lose",
    "contexto": "___ su dinero en juegos de azar."
  },
  {
    "infinitivo": "recordar",
    "tiempo": "futuro",
    "sujeto": "yo",
    "forma": "recordaré",
    "traducción": "remember",
    "contexto": "___ la fecha de mi cumpleaños.",
    "tags": [
      "ar",
      "stem-change"
    ]
  },
  {
    "infinitivo": "recordar",
    "tiempo": "futuro",
    "sujeto": "tú",
    "forma": "recordarás",
    "traducción": "remember",
    "contexto": "¿___ dónde pusiste el libro?"
  },
  {
    "infinitivo": "recordar",
    "tiempo": "futuro",
    "sujeto": "él / ella / usted",
    "forma": "recordará",
    "traducción": "remembers",
    "contexto": "Mi madre ___ su juventud."
  },
  {
    "infinitivo": "recordar",
    "tiempo": "futuro",
    "sujeto": "nosotros / nosotras",
    "forma": "recordaremos",
    "traducción": "remember",
    "contexto": "___ el viaje a la playa."
  },
  {
    "infinitivo": "recordar",
    "tiempo": "futuro",
    "sujeto": "vosotros / vosotras",
    "forma": "recordaréis",
    "traducción": "remember (en España)",
    "contexto": "___ los momentos felices. (España)"
  },
  {
    "infinitivo": "recordar",
    "tiempo": "futuro",
    "sujeto": "ellos / ellas / ustedes",
    "forma": "recordarán",
    "traducción": "remember",
    "contexto": "___ a su profesor de primaria con cariño."
  },
  {
    "infinitivo": "pagar",
    "tiempo": "futuro",
    "sujeto": "yo",
    "forma": "pagaré",
    "traducción": "pay",
    "contexto": "___ el alquiler a principios del próximo mes.",
    "tags": [
      "ar"
    ]
  },
  {
    "infinitivo": "pagar",
    "tiempo": "futuro",
    "sujeto": "tú",
    "forma": "pagarás",
    "traducción": "pay",
    "contexto": "¿___ con tarjeta de crédito o en efectivo?"
  },
  {
    "infinitivo": "pagar",
    "tiempo": "futuro",
    "sujeto": "él / ella / usted",
    "forma": "pagará",
    "traducción": "pays",
    "contexto": "Mi amigo ___ la cena de todos."
  },
  {
    "infinitivo": "pagar",
    "tiempo": "futuro",
    "sujeto": "nosotros / nosotras",
    "forma": "pagaremos",
    "traducción": "pay",
    "contexto": "___ la cuenta a la camarera."
  },
  {
    "infinitivo": "pagar",
    "tiempo": "futuro",
    "sujeto": "vosotros / vosotras",
    "forma": "pagaréis",
    "traducción": "pay (en España)",
    "contexto": "___ el viaje en cómodos plazos. (España)"
  },
  {
    "infinitivo": "pagar",
    "tiempo": "futuro",
    "sujeto": "ellos / ellas / ustedes",
    "forma": "pagarán",
    "traducción": "pay",
    "contexto": "___ sus deudas a tiempo."
  },
  {
    "infinitivo": "suponer",
    "tiempo": "futuro",
    "sujeto": "yo",
    "forma": "supondré",
    "traducción": "suppose",
    "contexto": "___ que la solución funcionará.",
    "tags": [
      "er",
      "yo-irregular"
    ]
  },
  {
    "infinitivo": "suponer",
    "tiempo": "futuro",
    "sujeto": "tú",
    "forma": "supondrás",
    "traducción": "suppose",
    "contexto": "¿___ que él tiene la razón?"
  },
  {
    "infinitivo": "suponer",
    "tiempo": "futuro",
    "sujeto": "él / ella / usted",
    "forma": "supondrá",
    "traducción": "supposes",
    "contexto": "Esa tarea ___ un gran desafío."
  },
  {
    "infinitivo": "suponer",
    "tiempo": "futuro",
    "sujeto": "nosotros / nosotras",
    "forma": "supondremos",
    "traducción": "suppose",
    "contexto": "___ que la reunión terminará pronto."
  },
  {
    "infinitivo": "suponer",
    "tiempo": "futuro",
    "sujeto": "vosotros / vosotras",
    "forma": "supondréis",
    "traducción": "suppose (en España)",
    "contexto": "¿___ que sabéis la respuesta? (España)"
  },
  {
    "infinitivo": "suponer",
    "tiempo": "futuro",
    "sujeto": "ellos / ellas / ustedes",
    "forma": "supondrán",
    "traducción": "suppose",
    "contexto": "___ que el nuevo sistema funcionará mejor."
  },
  {
    "infinitivo": "traer",
    "tiempo": "futuro",
    "sujeto": "yo",
    "forma": "traeré",
    "traducción": "bring",
    "contexto": "___ mi almuerzo de casa mañana.",
    "tags": [
      "er",
      "yo-irregular"
    ]
  },
  {
    "infinitivo": "traer",
    "tiempo": "futuro",
    "sujeto": "tú",
    "forma": "traerás",
    "traducción": "bring",
    "contexto": "___ las bebidas para la fiesta."
  },
  {
    "infinitivo": "traer",
    "tiempo": "futuro",
    "sujeto": "él / ella / usted",
    "forma": "traerá",
    "traducción": "brings",
    "contexto": "Mi hermana ___ regalos de su viaje."
  },
  {
    "infinitivo": "traer",
    "tiempo": "futuro",
    "sujeto": "nosotros / nosotras",
    "forma": "traeremos",
    "traducción": "bring",
    "contexto": "___ un postre para la cena."
  },
  {
    "infinitivo": "traer",
    "tiempo": "futuro",
    "sujeto": "vosotros / vosotras",
    "forma": "traeréis",
    "traducción": "bring (en España)",
    "contexto": "¿Qué ___ a la fiesta esta noche? (España)"
  },
  {
    "infinitivo": "traer",
    "tiempo": "futuro",
    "sujeto": "ellos / ellas / ustedes",
    "forma": "traerán",
    "traducción": "bring",
    "contexto": "___ sus instrumentos para el concierto."
  },
  {
    "infinitivo": "venir",
    "tiempo": "futuro",
    "sujeto": "yo",
    "forma": "vendré",
    "traducción": "come",
    "contexto": "___ a tu casa mañana.",
    "tags": [
      "ir",
      "stem-change",
      "yo-irregular"
    ]
  },
  {
    "infinitivo": "venir",
    "tiempo": "futuro",
    "sujeto": "tú",
    "forma": "vendrás",
    "traducción": "come",
    "contexto": "___ a la reunión si puedes."
  },
  {
    "infinitivo": "venir",
    "tiempo": "futuro",
    "sujeto": "él / ella / usted",
    "forma": "vendrá",
    "traducción": "comes",
    "contexto": "Mi primo ___ a visitarnos."
  },
  {
    "infinitivo": "venir",
    "tiempo": "futuro",
    "sujeto": "nosotros / nosotras",
    "forma": "vendremos",
    "traducción": "come",
    "contexto": "___ a la cena."
  },
  {
    "infinitivo": "venir",
    "tiempo": "futuro",
    "sujeto": "vosotros / vosotras",
    "forma": "vendréis",
    "traducción": "come (en España)",
    "contexto": "¿___ a la fiesta esta noche? (España)"
  },
  {
    "infinitivo": "venir",
    "tiempo": "futuro",
    "sujeto": "ellos / ellas / ustedes",
    "forma": "vendrán",
    "traducción": "come",
    "contexto": "___ a visitarnos el fin de semana."
  },
  {
    "infinitivo": "luchar",
    "tiempo": "futuro",
    "sujeto": "yo",
    "forma": "lucharé",
    "traducción": "fight / struggle",
    "contexto": "___ por mis sueños cada día.",
    "tags": [
      "ar"
    ]
  },
  {
    "infinitivo": "luchar",
    "tiempo": "futuro",
    "sujeto": "tú",
    "forma": "lucharás",
    "traducción": "fight / struggle",
    "contexto": "¿___ por tus derechos en el trabajo?"
  },
  {
    "infinitivo": "luchar",
    "tiempo": "futuro",
    "sujeto": "él / ella / usted",
    "forma": "luchará",
    "traducción": "fights / struggles",
    "contexto": "Mi amigo ___ contra una enfermedad."
  },
  {
    "infinitivo": "luchar",
    "tiempo": "futuro",
    "sujeto": "nosotros / nosotras",
    "forma": "lucharemos",
    "traducción": "fight / struggle",
    "contexto": "___ juntos por un mundo más justo."
  },
  {
    "infinitivo": "luchar",
    "tiempo": "futuro",
    "sujeto": "vosotros / vosotras",
    "forma": "lucharéis",
    "traducción": "fight / struggle (en España)",
    "contexto": "___ por vuestras metas con mucha pasión. (España)"
  },
  {
    "infinitivo": "luchar",
    "tiempo": "futuro",
    "sujeto": "ellos / ellas / ustedes",
    "forma": "lucharán",
    "traducción": "fight / struggle",
    "contexto": "___ por la victoria en el partido."
  },
  {
    "infinitivo": "tratar",
    "tiempo": "futuro",
    "sujeto": "yo",
    "forma": "trataré",
    "traducción": "treat / try",
    "contexto": "___ de ser más organizado.",
    "tags": [
      "ar"
    ]
  },
  {
    "infinitivo": "tratar",
    "tiempo": "futuro",
    "sujeto": "tú",
    "forma": "tratarás",
    "traducción": "treat / try",
    "contexto": "___ a todos con respeto."
  },
  {
    "infinitivo": "tratar",
    "tiempo": "futuro",
    "sujeto": "él / ella / usted",
    "forma": "tratará",
    "traducción": "treats / tries",
    "contexto": "Mi hermana ___ de estudiar más para el examen."
  },
  {
    "infinitivo": "tratar",
    "tiempo": "futuro",
    "sujeto": "nosotros / nosotras",
    "forma": "trataremos",
    "traducción": "treat / try",
    "contexto": "___ de terminar el proyecto a tiempo."
  },
  {
    "infinitivo": "tratar",
    "tiempo": "futuro",
    "sujeto": "vosotros / vosotras",
    "forma": "trataréis",
    "traducción": "treat / try (en España)",
    "contexto": "___ de ayudar a vuestros vecinos. (España)"
  },
  {
    "infinitivo": "tratar",
    "tiempo": "futuro",
    "sujeto": "ellos / ellas / ustedes",
    "forma": "tratarán",
    "traducción": "treat / try",
    "contexto": "___ de resolver el problema."
  },
  {
    "infinitivo": "volver",
    "tiempo": "futuro",
    "sujeto": "yo",
    "forma": "volveré",
    "traducción": "return / turn",
    "contexto": "___ al trabajo después del descanso.",
    "tags": [
      "er",
      "stem-change"
    ]
  },
  {
    "infinitivo": "volver",
    "tiempo": "futuro",
    "sujeto": "tú",
    "forma": "volverás",
    "traducción": "return / turn",
    "contexto": "___ a leer ese libro otra vez."
  },
  {
    "infinitivo": "volver",
    "tiempo": "futuro",
    "sujeto": "él / ella / usted",
    "forma": "volverá",
    "traducción": "returns / turns",
    "contexto": "Mi padre ___ a su trabajo después de la pausa."
  },
  {
    "infinitivo": "volver",
    "tiempo": "futuro",
    "sujeto": "nosotros / nosotras",
    "forma": "volveremos",
    "traducción": "return / turn",
    "contexto": "___ al gimnasio mañana."
  },
  {
    "infinitivo": "volver",
    "tiempo": "futuro",
    "sujeto": "vosotros / vosotras",
    "forma": "volveréis",
    "traducción": "return / turn (en España)",
    "contexto": "¿A qué hora ___ de clase? (España)"
  },
  {
    "infinitivo": "volver",
    "tiempo": "futuro",
    "sujeto": "ellos / ellas / ustedes",
    "forma": "volverán",
    "traducción": "return / turn",
    "contexto": "___ a la casa de sus padres."
  },
  {
    "infinitivo": "preocuparse",
    "tiempo": "futuro",
    "sujeto": "yo",
    "forma": "me preocuparé",
    "traducción": "worry / get worried",
    "contexto": "___ demasiado por lo que diga la gente.",
    "tags": [
      "ar",
      "reflexive"
    ]
  },
  {
    "infinitivo": "preocuparse",
    "tiempo": "futuro",
    "sujeto": "tú",
    "forma": "te preocuparás",
    "traducción": "worry / get worried",
    "contexto": "¿___ por el examen?"
  },
  {
    "infinitivo": "preocuparse",
    "tiempo": "futuro",
    "sujeto": "él",
    "forma": "se preocupará",
    "traducción": "worries / gets worried",
    "contexto": "Mi amigo ___ si no recibe el correo."
  },
  {
    "infinitivo": "preocuparse",
    "tiempo": "futuro",
    "sujeto": "ella",
    "forma": "se preocupará",
    "traducción": "worries / gets worried",
    "contexto": "___ si llega tarde a la reunión."
  },
  {
    "infinitivo": "preocuparse",
    "tiempo": "futuro",
    "sujeto": "nosotros",
    "forma": "nos preocuparemos",
    "traducción": "worry / get worried",
    "contexto": "___ por el futuro."
  },
  {
    "infinitivo": "preocuparse",
    "tiempo": "futuro",
    "sujeto": "vosotros",
    "forma": "os preocuparéis",
    "traducción": "worry / get worried (en España)",
    "contexto": "___ por vuestra salud. (España)"
  },
  {
    "infinitivo": "preocuparse",
    "tiempo": "futuro",
    "sujeto": "ellos",
    "forma": "se preocuparán",
    "traducción": "worry / get worried",
    "contexto": "___ por sus hijos."
  },
  {
    "infinitivo": "aburrirse",
    "tiempo": "futuro",
    "sujeto": "yo",
    "forma": "me aburriré",
    "traducción": "get bored",
    "contexto": "___ cuando no tenga nada que hacer.",
    "tags": [
      "ar",
      "reflexive"
    ]
  },
  {
    "infinitivo": "aburrirse",
    "tiempo": "futuro",
    "sujeto": "tú",
    "forma": "te aburrirás",
    "traducción": "get bored",
    "contexto": "¿___ en las reuniones largas?"
  },
  {
    "infinitivo": "aburrirse",
    "tiempo": "futuro",
    "sujeto": "él",
    "forma": "se aburrirá",
    "traducción": "gets bored",
    "contexto": "___ en clase cuando no participe."
  },
  {
    "infinitivo": "aburrirse",
    "tiempo": "futuro",
    "sujeto": "ella",
    "forma": "se aburrirá",
    "traducción": "gets bored",
    "contexto": "___ si repite la misma actividad."
  },
  {
    "infinitivo": "aburrirse",
    "tiempo": "futuro",
    "sujeto": "nosotros",
    "forma": "nos aburriremos",
    "traducción": "get bored",
    "contexto": "___ en casa."
  },
  {
    "infinitivo": "aburrirse",
    "tiempo": "futuro",
    "sujeto": "vosotros",
    "forma": "os aburriréis",
    "traducción": "get bored (en España)",
    "contexto": "___ en el viaje si no lleváis juegos. (España)"
  },
  {
    "infinitivo": "aburrirse",
    "tiempo": "futuro",
    "sujeto": "ellos",
    "forma": "se aburrirán",
    "traducción": "get bored",
    "contexto": "___ si tienen que esperar mucho tiempo."
  }
]
